Workbook
Name Balance_Sheet: 'Historical FS'!$B$48:$M$67
Name Cash_Flow_Statements: 'Historical FS'!$B$71
Name Cashflow_statement: 'Historical FS'!$B$71:$M$108
Name Income_Statement: 'Historical FS'!$B$5:$M$45

Sheet Data Sheet
A1: COMPANY NAME | B1: TATA MOTORS LTD | E1: =IF(B2<>B3, "A NEW VERSION OF THE WORKSHEET IS AVAILABLE", "")
A2: LATEST VERSION | B2: 2.1 | E2: PLEASE DO NOT MAKE ANY CHANGES TO THIS SHEET
A3: CURRENT VERSION | B3: 2.1
A5: META
A6: Number of shares | B6: =IF(B9>0, B9/B8, 0) -> 368.11892
A7: Face Value | B7: 2
A8: Current Price | B8: 680.65
A9: Market Capitalization | B9: 250560.14
A15: PROFIT & LOSS
A16: Report Date | B16: 42094 | C16: 42460 | D16: 42825 | E16: 43190 | F16: 43555 | G16: 43921 | H16: 44286 | I16: 44651 | J16: 45016 | K16: 45382
A17: Sales | B17: 263158.98 | C17: 273045.6 | D17: 269692.51 | E17: 291550.48 | F17: 301938.4 | G17: 261067.97 | H17: 249794.75 | I17: 278453.62 | J17: 345966.97 | K17: 437927.77
A18: Raw Material Cost | B18: 163250.36 | C18: 166134.01 | D18: 173294.08 | E18: 187896.58 | F18: 194267.91 | G18: 164899.82 | H18: 153607.36 | I18: 179295.33 | J18: 231251.26 | K18: 274321.23
A19: Change in Inventory | B19: 3330.35 | C19: 2750.99 | D19: 7399.92 | E19: 2046.58 | F19: -2053.28 | G19: -2231.19 | H19: -4684.16 | I19: -1590.49 | J19: 4781.62 | K19: 1565.53
A20: Power and Fuel | B20: 1121.75 | C20: 1143.63 | D20: 1159.82 | E20: 1308.08 | F20: 1585.93 | G20: 1264.95 | H20: 1112.87 | I20: 2178.29 | J20: 2513.33 | K20: 2195.12
A21: Other Mfr. Exp | B21: 16173.17 | C21: 12101.53 | D21: 10067.37 | E21: 10971.66 | F21: 11694.54 | G21: 11541.51 | H21: 8273.17 | I21: 9427.38 | J21: 11765.97 | K21: 17114.33
A22: Employee Cost | B22: 25641.95 | C22: 28880.89 | D22: 28332.89 | E22: 30300.09 | F22: 33243.87 | G22: 30438.6 | H22: 27648.48 | I22: 30808.52 | J22: 33654.7 | K22: 42486.64
A23: Selling and admin | B23: 23603.01 | C23: 21991.9 | D23: 30039.38 | E23: 31004.58 | F23: 32719.8 | G23: 29248.32 | H23: 23015.79 | I23: 29205.4 | J23: 34839.19 | K23: 42765.33
A24: Other Expenses | B24: -2539.56 | C24: 7149.38 | D24: 4610.2 | E24: 658.39 | F24: 1708.74 | G24: 3456.51 | H24: -834.51 | I24: 1228.12 | J24: 4908.34 | K24: 1072.31
A25: Other Income | B25: 714.03 | C25: -2669.62 | D25: 1869.1 | E25: 5932.73 | F25: -26686.25 | G25: 101.71 | H25: -11117.83 | I25: 2424.05 | J25: 6663.97 | K25: 5672.66
A26: Depreciation | B26: 13388.63 | C26: 16710.78 | D26: 17904.99 | E26: 21553.59 | F26: 23590.63 | G26: 21425.43 | H26: 23546.71 | I26: 24835.69 | J26: 24860.36 | K26: 27270.13
A27: Interest | B27: 4861.49 | C27: 4889.08 | D27: 4238.01 | E27: 4681.79 | F27: 5758.6 | G27: 7243.33 | H27: 8097.17 | I27: 9311.86 | J27: 10225.48 | K27: 9985.76
... A30: Net profit | B30: 13986.29 | C30: 11579.31 | D30: 7454.36 | E30: 8988.91 | F30: -28826.23 | G30: -12070.85 | H30: -13451.39 | I30: -11441.47 | J30: 2414.29 | K30: 31399.09
A31: Dividend Amount | C31: 67.92 | J31: 766.02 | K31: 2299.5
B34: =B30+B26+B27+B29 -> 39879.32 | C34: =C30+C26+C27+C29 -> 36204.22 | D34: =D30+D26+D27+D29 -> 32848.59 | E34: =E30+E26+E27+E29 -> 39566.22 | F34: =F30+F26+F27+F29 -> -1914.45 | G34: =G30+G26+G27+G29 -> 16993.16 | H34: =H30+H26+H27+H29 -> 20734.35 | I34: =I30+I26+I27+I29 -> 26937.37 | ... K34: =K30+K26+K27+K29 -> 64803.34
A35: EBIT | B35: =B30+B27+B29 -> 26490.69 | C35: =C30+C27+C29 -> 19493.44 | D35: =D30+D27+D29 -> 14943.6 | E35: =E30+E27+E29 -> 18012.63 | F35: =F30+F27+F29 -> -25505.08 | G35: =G30+G27+G29 -> -4432.27 | H35: =H30+H27+H29 -> -2812.36 | I35: =I30+I27+I29 -> 2101.68 | ... K35: =K30+K27+K29 -> 37533.21
A39: Quarters
A40: Report Date | B40: 44834 | C40: 44926 | D40: 45016 | E40: 45107 | F40: 45199 | G40: 45291 | H40: 45382 | I40: 45473 | J40: 45565 | K40: 45657
A41: Sales | B41: 79611.37 | C41: 88488.59 | D41: 105932.35 | E41: 102236 | F41: 105129 | G41: 110577 | H41: 119986 | I41: 108048 | J41: 101450 | K41: 113575
A42: Expenses | B42: 74039.06 | C42: 77668.35 | D42: 92817.95 | E42: 89019 | F42: 91362 | G42: 95159 | H42: 102851 | I42: 92263 | J42: 89291 | K42: 100532
A43: Other Income | B43: 1351.14 | C43: 1129.98 | D43: 1452.86 | E43: 895 | F43: 1557 | G43: 1604 | H43: 1619 | I43: 1747 | J43: 1647 | K43: 1764
A44: Depreciation | B44: 5897.34 | C44: 6071.78 | D44: 7050.2 | E44: 6633 | F44: 6637 | G44: 6850 | H44: 7151 | I44: 6574 | J44: 6005 | K44: 5408
A45: Interest | B45: 2487.26 | C45: 2675.83 | D45: 2641.67 | E45: 2615 | F45: 2652 | G45: 2485 | H45: 2234 | I45: 2088 | J45: 2034 | K45: 1725
A46: Profit before tax | B46: -1461.15 | C46: 3202.61 | D46: 4875.39 | E46: 4864 | F46: 6035 | G46: 7687 | H46: 9369 | I46: 8870 | J46: 5767 | K46: 7674
A47: Tax | B47: -457.08 | C47: 262.83 | D47: -620.65 | E47: 1563 | F47: 2203 | G47: 542 | H47: -8160 | I47: 3178 | J47: 2317 | K47: 2096
A48: Net profit | B48: -944.61 | C48: 2957.71 | D48: 5407.79 | E48: 3203 | F48: 3764 | G48: 7025 | H48: 17407 | I48: 5566 | J48: 3343 | K48: 5451
A49: Operating Profit | B49: 5572.31 | C49: 10820.24 | D49: 13114.4 | E49: 13217 | F49: 13767 | G49: 15418 | H49: 17135 | I49: 15785 | J49: 12159 | K49: 13043
A54: BALANCE SHEET
A55: Report Date | B55: 42094 | C55: 42460 | D55: 42825 | E55: 43190 | F55: 43555 | G55: 43921 | H55: 44286 | I55: 44651 | J55: 45016 | K55: 45382
A56: Equity Share Capital | B56: 643.78 | C56: 679.18 | D56: 679.22 | E56: 679.22 | F56: 679.22 | G56: 719.54 | H56: 765.81 | I56: 765.88 | J56: 766.02 | K56: 766.5
A57: Reserves | B57: 55618.14 | C57: 78273.23 | D57: 57382.67 | E57: 94748.69 | F57: 59500.34 | G57: 62358.99 | H57: 54480.91 | I57: 43795.36 | J57: 44555.77 | K57: 84151.52
A58: Borrowings | B58: 73610.39 | C58: 69359.96 | D58: 78603.98 | E58: 88950.47 | F58: 106175.34 | G58: 124787.64 | H58: 142130.57 | I58: 146449.03 | J58: 134113.44 | K58: 107262.5
A59: Other Liabilities | B59: 107442.48 | C59: 114871.75 | D59: 135914.49 | E59: 142813.43 | F59: 139348.59 | G59: 132313.22 | H59: 144192.62 | I59: 138051.22 | J59: 155239.2 | K59: 177340.09
A60: Total | B60: 237314.79 | C60: 263184.12 | D60: 272580.36 | E60: 327191.81 | F60: 305703.49 | G60: 320179.39 | H60: 341569.91 | I60: 329061.49 | J60: 334674.43 | K60: 369520.61
A61: Net Block | B61: 88479.49 | C61: 107231.76 | D61: 95944.08 | E61: 121413.86 | F61: 111234.47 | G61: 127107.14 | H61: 138707.61 | I61: 138855.45 | J61: 132079.76 | K61: 121285.46
A62: Capital Work in Progress | B62: 28640.09 | C62: 25918.94 | D62: 33698.84 | E62: 40033.5 | F62: 31883.84 | G62: 35622.29 | H62: 20963.93 | I62: 10251.09 | J62: 14274.5 | K62: 35698.43
A63: Investments | B63: 15336.74 | C63: 23767.02 | D63: 20337.92 | E63: 20812.75 | F63: 15770.72 | G63: 16308.48 | H63: 24620.28 | I63: 29379.53 | J63: 26379.16 | K63: 22971.07
A64: Other Assets | B64: 104858.47 | C64: 106266.4 | D64: 122599.52 | E64: 144931.7 | F64: 146814.46 | G64: 141141.48 | H64: 157278.09 | I64: 150575.42 | J64: 161941.01 | K64: 189565.65
A65: Total | B65: 237314.79 | C65: 263184.12 | D65: 272580.36 | E65: 327191.81 | F65: 305703.49 | G65: 320179.39 | H65: 341569.91 | I65: 329061.49 | J65: 334674.43 | K65: 369520.61
A66: Receivables | B66: 12579.2 | C66: 13570.91 | D66: 14075.55 | E66: 19893.3 | F66: 18996.17 | G66: 11172.69 | H66: 12679.08 | I66: 12442.12 | J66: 15737.97 | K66: 16951.81
... A69: No. of Equity Shares | B69: 3218930067 | C69: 3395930306 | D69: 3396100719 | E69: 3396100719 | F69: 3396100719 | G69: 3597726185 | H69: 3829060661 | I69: 3829414903 | J69: 3830097221 | K69: 3832491897
A70: New Bonus Shares
A71: Face value | B71: 2 | C71: 2 | D71: 2 | E71: 2 | F71: 2 | G71: 2 | H71: 2 | I71: 2 | J71: 2 | K71: 2
B73: =SUM(B66:B68) -> 73967.3 | C73: =SUM(C66:C68) -> 76687.04 | D73: =SUM(D66:D68) -> 85238.74 | E73: =SUM(E66:E68) -> 96644.84 | F73: =SUM(F66:F68) -> 90658.72 | G73: =SUM(G66:G68) -> 82356.54 | H73: =SUM(H66:H68) -> 95560.13 | I73: =SUM(I66:I68) -> 88351.65 | ... K73: =SUM(K66:K68) -> 110546.79
A74: Other Assets | B74: =B64-B73 -> 30891.17 | C74: =C64-C73 -> 29579.36 | D74: =D64-D73 -> 37360.78 | E74: =E64-E73 -> 48286.86 | F74: =F64-F73 -> 56155.74 | G74: =G64-G73 -> 58784.94 | H74: =H64-H73 -> 61717.96 | I74: =I64-I73 -> 62223.77 | ... K74: =K64-K73 -> 79018.86
A79: CASH FLOW:
A80: Report Date | B80: 42094 | C80: 42460 | D80: 42825 | E80: 43190 | F80: 43555 | G80: 43921 | H80: 44286 | I80: 44651 | J80: 45016 | K80: 45382
A81: Cash from Operating Activity | B81: 35531.26 | C81: 37899.54 | D81: 30199.25 | E81: 23857.42 | F81: 18890.75 | G81: 26632.94 | H81: 29000.51 | I81: 14282.83 | J81: 35388.01 | K81: 67915.36
A82: Cash from Investing Activity | B82: -36232.35 | C82: -36693.9 | D82: -39571.4 | E82: -25139.14 | F82: -20878.07 | G82: -33114.55 | H82: -25672.5 | I82: -4443.66 | J82: -15417.17 | K82: -22781.56
A83: Cash from Financing Activity | B83: 5201.44 | C83: -3795.12 | D83: 6205.3 | E83: 2011.71 | F83: 8830.37 | G83: 3389.61 | H83: 9904.2 | I83: -3380.17 | J83: -26242.9 | K83: -37005.99
A84: Net Cash Flow | B84: 4500.35 | C84: -2589.48 | D84: -3166.85 | E84: 729.99 | F84: 6843.05 | G84: -3092 | H84: 13232.21 | I84: 6459 | J84: -6272.06 | K84: 8127.81
A89: PRICE: | B89: 544.37 | C89: 386.6 | D89: 465.85 | E89: 326.85 | F89: 174.25 | G89: 71.05 | H89: 301.8 | I89: 433.75 | J89: 420.8 | K89: 992.8
A91: DERIVED:
A92: Adjusted Equity Shares in Cr | B92: 288.74 | C92: 288.72 | D92: 288.73 | E92: 288.73 | F92: 288.73 | G92: 308.9 | H92: 332.03 | I92: 332.07 | J92: 332.13 | K92: 332.37

Sheet Cash Flow Data
C2: 42064 | D2: 42430 | E2: 42795 | F2: 43160 | G2: 43525 | H2: 43891 | I2: 44256 | J2: 44621 | K2: 44986 | L2: 45352
B3: Cash from Operating Activity - | C3: 35531 | D3: 37900 | E3: 30199 | F3: 23857 | G3: 18891 | H3: 26633 | I3: 29001 | J3: 14283 | K3: 35388 | L3: 67915
B4: Profit from operations | C4: 43397 | D4: 38626 | E4: 28840 | F4: 33312 | G4: 28771 | H4: 23352 | I4: 31198 | J4: 26943 | K4: 41694 | L4: 65106
B5: Receivables | C5: -3179 | D5: -2223 | E5: -4152 | F5: -10688 | G5: -9109 | H5: 9950 | I5: -5505 | J5: 185 | K5: -2213 | L5: -1875
B6: Inventory | C6: -3692 | D6: -5743 | E6: -6621 | F6: -3560 | G6: 2069 | H6: 2326 | I6: 3814 | J6: 472 | K6: -5665 | L6: -7265
B7: Payables | C7: 3598 | D7: 3947 | E7: 9301 | F7: 7320 | G7: -4692 | H7: -8085 | I7: 5748 | J7: -7012 | K7: 6945 | L7: 13706
B8: Loans Advances | C8: 0 | D8: -520 | E8: 0 | F8: 0 | G8: 0 | H8: 0 | I8: 0 | J8: 0 | K8: 0 | L8: 0
B9: Other WC items | C9: -398 | D9: 5852 | E9: 4727 | F9: 494 | G9: 4512 | H9: 875 | I9: -4150 | J9: -4396 | K9: -2194 | L9: 2760
B10: Working capital changes | C10: -3672 | D10: 1313 | E10: 3254 | F10: -6434 | G10: -7221 | H10: 5065 | I10: -93 | J10: -10750 | K10: -3127 | L10: 7325
B11: Direct taxes | C11: -4194 | D11: -2040 | E11: -1895 | F11: -3021 | G11: -2659 | H11: -1785 | I11: -2105 | J11: -1910 | K11: -3179 | L11: -4516
B12: Cash from Investing Activity - | C12: -36232 | D12: -36694 | E12: -39571 | F12: -25139 | G12: -20878 | H12: -33115 | I12: -25672 | J12: -4444 | K12: -15417 | L12: -22782
B13: Fixed assets purchased | C13: -31962 | D13: -31503 | E13: -16072 | F13: -35079 | G13: -35304 | H13: -29702 | I13: -20205 | J13: -15168 | K13: -19230 | L13: -31414
B14: Fixed assets sold | C14: 74 | D14: 59 | E14: 53 | F14: 30 | G14: 67 | H14: 171 | I14: 351 | J14: 230 | K14: 285 | L14: 231
... B33: Net Cash Flow | C33: 4500 | D33: -2589 | E33: -3167 | F33: 730 | G33: 6843 | H33: -3092 | I33: 13232 | J33: 6459 | K33: -6272 | L33: 8128

Sheet Historical FS
B2: ="Historical Financial Statement - "&'Data Sheet'!B1 -> Historical Financial Statement - TATA MOTORS LTD
B3: Year | C3: ='Data Sheet'!B16 -> 42094 | D3: ='Data Sheet'!C16 -> 42460 | E3: ='Data Sheet'!D16 -> 42825 | F3: ='Data Sheet'!E16 -> 43190 | G3: ='Data Sheet'!F16 -> 43555 | H3: ='Data Sheet'!G16 -> 43921 | I3: ='Data Sheet'!H16 -> 44286 | J3: ='Data Sheet'!I16 -> 44651 | ... L3: ='Data Sheet'!K16 -> 45382 | M3: LTM
A5: # | B5: Income Statement | C5: 42094 | D5: 42460 | E5: 42825 | F5: 43190 | G5: 43555 | H5: 43921 | I5: 44286 | J5: 44651 | K5: 45016 | L5: 45382 | M5: LTM
B6: Sales | C6: =IFERROR('Data Sheet'!B17,0) -> 263158.98 | D6: =IFERROR('Data Sheet'!C17,0) -> 273045.6 | E6: =IFERROR('Data Sheet'!D17,0) -> 269692.51 | F6: =IFERROR('Data Sheet'!E17,0) -> 291550.48 | G6: =IFERROR('Data Sheet'!F17,0) -> 301938.4 | H6: =IFERROR('Data Sheet'!G17,0) -> 261067.97 | I6: =IFERROR('Data Sheet'!H17,0) -> 249794.75 | J6: =IFERROR('Data Sheet'!I17,0) -> 278453.62 | ... L6: =IFERROR('Data Sheet'!K17,0) -> 437927.77 | M6: =IFERROR(SUM('Data Sheet'!H41:K41),0) -> 443059
B7: Sales Growth | C7: - | D7: =D6/C6-1 -> 0.037569001 | E7: =E6/D6-1 -> -0.01228033 | F7: =F6/E6-1 -> 0.081047746 | G7: =G6/F6-1 -> 0.035629919 | H7: =H6/G6-1 -> -0.13536016 | I7: =I6/H6-1 -> -0.043181168 | J7: =J6/I6-1 -> 0.11472967 | K7: =K6/J6-1 -> 0.24245815 | ... M7: =M6/L6-1 -> 0.011717069
B9: COGS | C9: =IFERROR(SUM('Data Sheet'!B18,'Data Sheet'!B20:B22,-1*'Data Sheet'!B19),0) -> 202856.88 | D9: =IFERROR(SUM('Data Sheet'!C18,'Data Sheet'!C20:C22,-1*'Data Sheet'!C19),0) -> 205509.07 | E9: =IFERROR(SUM('Data Sheet'!D18,'Data Sheet'!D20:D22,-1*'Data Sheet'!D19),0) -> 205454.24 | F9: =IFERROR(SUM('Data Sheet'!E18,'Data Sheet'!E20:E22,-1*'Data Sheet'!E19),0) -> 228429.83 | G9: =IFERROR(SUM('Data Sheet'!F18,'Data Sheet'!F20:F22,-1*'Data Sheet'!F19),0) -> 242845.53 | H9: =IFERROR(SUM('Data Sheet'!G18,'Data Sheet'!G20:G22,-1*'Data Sheet'!G19),0) -> 210376.07 | I9: =IFERROR(SUM('Data Sheet'!H18,'Data Sheet'!H20:H22,-1*'Data Sheet'!H19),0) -> 195326.04 | J9: =IFERROR(SUM('Data Sheet'!I18,'Data Sheet'!I20:I22,-1*'Data Sheet'!I19),0) -> 223300.01 | ... L9: =IFERROR(SUM('Data Sheet'!K18,'Data Sheet'!K20:K22,-1*'Data Sheet'!K19),0) -> 334551.79 | M9: =IFERROR(SUM('Data Sheet'!H42:K42),0) -> 384937
B10: COGS % of Sales | C10: =C9/C6 -> 0.77085297 | D10: =D9/D6 -> 0.75265476 | E10: =E9/E6 -> 0.76180922 | F10: =F9/F6 -> 0.7835001 | G10: =G9/G6 -> 0.80428833 | H10: =H9/H6 -> 0.80582873 | I10: =I9/I6 -> 0.78194614 | J10: =J9/J6 -> 0.80192892 | ... M10: =M9/M6 -> 0.86881657
B12: Gross Profit | C12: =C6-C9 -> 60302.1 | D12: =D6-D9 -> 67536.53 | E12: =E6-E9 -> 64238.27 | F12: =F6-F9 -> 63120.65 | G12: =G6-G9 -> 59092.87 | H12: =H6-H9 -> 50691.9 | I12: =I6-I9 -> 54468.71 | J12: =J6-J9 -> 55153.61 | ... M12: =M6-M9 -> 58122
B13: Gross Margin | C13: =C12/C6 -> 0.22914703 | D13: =D12/D6 -> 0.24734524 | E13: =E12/E6 -> 0.23819078 | F13: =F12/F6 -> 0.2164999 | G13: =G12/G6 -> 0.19571167 | H13: =H12/H6 -> 0.19417127 | I13: =I12/I6 -> 0.21805386 | J13: =J12/J6 -> 0.19807108 | ... M13: =M12/M6 -> 0.13118343
B15: Selling & General Expenses | C15: =IFERROR(SUM('Data Sheet'!B23:B24),0) -> 21063.45 | D15: =IFERROR(SUM('Data Sheet'!C23:C24),0) -> 29141.28 | E15: =IFERROR(SUM('Data Sheet'!D23:D24),0) -> 34649.58 | F15: =IFERROR(SUM('Data Sheet'!E23:E24),0) -> 31662.97 | G15: =IFERROR(SUM('Data Sheet'!F23:F24),0) -> 34428.54 | H15: =IFERROR(SUM('Data Sheet'!G23:G24),0) -> 32704.83 | I15: =IFERROR(SUM('Data Sheet'!H23:H24),0) -> 22181.28 | J15: =IFERROR(SUM('Data Sheet'!I23:I24),0) -> 30433.52 | ... M15: =IFERROR(SUM('Data Sheet'!L23:L24),0) -> 0
B16: S&G % of Sales | C16: =C15/C6 -> 0.08004078 | D16: =D15/D6 -> 0.10672679 | E16: =E15/E6 -> 0.1284781 | F16: =F15/F6 -> 0.10860202 | G16: =G15/G6 -> 0.11402505 | H16: =H15/H6 -> 0.12527324 | I16: =I15/I6 -> 0.088798023 | J16: =J15/J6 -> 0.10929475 | ... M16: =M15/M6 -> 0
B18: EBITDA | C18: =C12-C15 -> 39238.65 | D18: =D12-D15 -> 38395.25 | E18: =E12-E15 -> 29588.69 | F18: =F12-F15 -> 31457.68 | G18: =G12-G15 -> 24664.33 | H18: =H12-H15 -> 17987.07 | I18: =I12-I15 -> 32287.43 | J18: =J12-J15 -> 24720.09 | ... M18: =M12-M15 -> 58122
B19: EBITDA % of Sales | C19: =C18/C6 -> 0.14910626 | D19: =D18/D6 -> 0.14061845 | E19: =E18/E6 -> 0.10971269 | F19: =F18/F6 -> 0.10789788 | G19: =G18/G6 -> 0.081686629 | H19: =H18/H6 -> 0.068898034 | I19: =I18/I6 -> 0.12925584 | J19: =J18/J6 -> 0.088776328 | ... M19: =M18/M6 -> 0.13118343
B21: Interest | C21: =IFERROR('Data Sheet'!B27,0) -> 4861.49 | D21: =IFERROR('Data Sheet'!C27,0) -> 4889.08 | E21: =IFERROR('Data Sheet'!D27,0) -> 4238.01 | F21: =IFERROR('Data Sheet'!E27,0) -> 4681.79 | G21: =IFERROR('Data Sheet'!F27,0) -> 5758.6 | H21: =IFERROR('Data Sheet'!G27,0) -> 7243.33 | I21: =IFERROR('Data Sheet'!H27,0) -> 8097.17 | J21: =IFERROR('Data Sheet'!I27,0) -> 9311.86 | ... L21: =IFERROR('Data Sheet'!K27,0) -> 9985.76 | M21: =IFERROR(SUM('Data Sheet'!H45:K45),0) -> 8081
B22: Interest % of Sales | C22: =C21/C6 -> 0.018473586 | D22: =D21/D6 -> 0.017905727 | E22: =E21/E6 -> 0.01571423 | F22: =F21/F6 -> 0.016058248 | G22: =G21/G6 -> 0.019072102 | H22: =H21/H6 -> 0.027744997 | I22: =I21/I6 -> 0.032415293 | J22: =J21/J6 -> 0.033441332 | ... M22: =M21/M6 -> 0.018239106
B24: Depreciation | C24: =IFERROR('Data Sheet'!B26,0) -> 13388.63 | D24: =IFERROR('Data Sheet'!C26,0) -> 16710.78 | E24: =IFERROR('Data Sheet'!D26,0) -> 17904.99 | F24: =IFERROR('Data Sheet'!E26,0) -> 21553.59 | G24: =IFERROR('Data Sheet'!F26,0) -> 23590.63 | H24: =IFERROR('Data Sheet'!G26,0) -> 21425.43 | I24: =IFERROR('Data Sheet'!H26,0) -> 23546.71 | J24: =IFERROR('Data Sheet'!I26,0) -> 24835.69 | ... L24: =IFERROR('Data Sheet'!K26,0) -> 27270.13 | M24: =IFERROR(SUM('Data Sheet'!H44:K44),0) -> 25138
B25: Depreciation of Sales | C25: =C24/C6 -> 0.050876584 | D25: =D24/D6 -> 0.061201426 | E25: =E24/E6 -> 0.066390387 | F25: =F24/F6 -> 0.073927472 | G25: =G24/G6 -> 0.078130605 | H25: =H24/H6 -> 0.082068398 | I25: =I24/I6 -> 0.094264231 | J25: =J24/J6 -> 0.089191478 | ... M25: =M24/M6 -> 0.056737365
B27: Earning Before Tax (EBT) | C27: =IFERROR(C18-SUM(C21,C24),0) -> 20988.53 | D27: =IFERROR(D18-SUM(D21,D24),0) -> 16795.39 | E27: =IFERROR(E18-SUM(E21,E24),0) -> 7445.69 | F27: =IFERROR(F18-SUM(F21,F24),0) -> 5222.3 | G27: =IFERROR(G18-SUM(G21,G24),0) -> -4684.9 | H27: =IFERROR(H18-SUM(H21,H24),0) -> -10681.69 | I27: =IFERROR(I18-SUM(I21,I24),0) -> 643.55 | J27: =IFERROR(J18-SUM(J21,J24),0) -> -9427.46 | ... M27: =IFERROR(M18-SUM(M21,M24),0) -> 24903
B28: EBT % of Sales | C28: =C27/C6 -> 0.079756085 | D28: =D27/D6 -> 0.061511301 | E28: =E27/E6 -> 0.027608071 | F28: =F27/F6 -> 0.017912164 | G28: =G27/G6 -> -0.015516079 | H28: =H27/H6 -> -0.04091536 | I28: =I27/I6 -> 0.0025763152 | J28: =J27/J6 -> -0.033856482 | ... M28: =M27/M6 -> 0.056206961
B30: Tax | C30: =IFERROR('Data Sheet'!B29,0) -> 7642.91 | D30: =IFERROR('Data Sheet'!C29,0) -> 3025.05 | E30: =IFERROR('Data Sheet'!D29,0) -> 3251.23 | F30: =IFERROR('Data Sheet'!E29,0) -> 4341.93 | G30: =IFERROR('Data Sheet'!F29,0) -> -2437.45 | H30: =IFERROR('Data Sheet'!G29,0) -> 395.25 | I30: =IFERROR('Data Sheet'!H29,0) -> 2541.86 | J30: =IFERROR('Data Sheet'!I29,0) -> 4231.29 | ... L30: =IFERROR('Data Sheet'!K29,0) -> -3851.64 | M30: =IFERROR(SUM('Data Sheet'!H47:K47),0) -> -569
B31: Effective Tax Rate | C31: =C30/C27 -> 0.36414699 | D31: =D30/D27 -> 0.18011192 | E31: =E30/E27 -> 0.43665933 | F31: =F30/F27 -> 0.83142102 | G31: =G30/G27 -> 0.52027791 | H31: =H30/H27 -> -0.037002572 | I31: =I30/I27 -> 3.9497475 | J31: =J30/J27 -> -0.44882609 | ... M31: =M30/M27 -> -0.022848653
B33: Net Profit | C33: =IFERROR(C27-C30,0) -> 13345.62 | D33: =IFERROR(D27-D30,0) -> 13770.34 | E33: =IFERROR(E27-E30,0) -> 4194.46 | F33: =IFERROR(F27-F30,0) -> 880.37 | G33: =IFERROR(G27-G30,0) -> -2247.45 | H33: =IFERROR(H27-H30,0) -> -11076.94 | I33: =IFERROR(I27-I30,0) -> -1898.31 | J33: =IFERROR(J27-J30,0) -> -13658.75 | ... M33: =IFERROR(M27-M30,0) -> 25472
B34: Net Margin | C34: =C33/C6 -> 0.050713147 | D34: =D33/D6 -> 0.050432382 | E34: =E33/E6 -> 0.015552749 | F34: =F33/F6 -> 0.0030196143 | G34: =G33/G6 -> -0.0074434057 | H34: =H33/H6 -> -0.042429334 | I34: =I33/I6 -> -0.0075994792 | J34: =J33/J6 -> -0.049052155 | ... M34: =M33/M6 -> 0.057491214
B36: No. Of Equity Shares | C36: =IFERROR('Data Sheet'!B92,0) -> 288.74 | D36: =IFERROR('Data Sheet'!C92,0) -> 288.72 | E36: =IFERROR('Data Sheet'!D92,0) -> 288.73 | F36: =IFERROR('Data Sheet'!E92,0) -> 288.73 | G36: =IFERROR('Data Sheet'!F92,0) -> 288.73 | H36: =IFERROR('Data Sheet'!G92,0) -> 308.9 | I36: =IFERROR('Data Sheet'!H92,0) -> 332.03 | J36: =IFERROR('Data Sheet'!I92,0) -> 332.07 | ... L36: =IFERROR('Data Sheet'!K92,0) -> 332.37 | M36: 332.37
B39: Earning Per Share | C39: =IFERROR(C33/C36,0) -> 46.220198 | D39: =IFERROR(D33/D36,0) -> 47.694444 | E39: =IFERROR(E33/E36,0) -> 14.527275 | F39: =IFERROR(F33/F36,0) -> 3.0491116 | G39: =IFERROR(G33/G36,0) -> -7.7839158 | H39: =IFERROR(H33/H36,0) -> -35.859307 | I39: =IFERROR(I33/I36,0) -> -5.7172846 | J39: =IFERROR(J33/J36,0) -> -41.132141 | ... M39: =IFERROR(M33/M36,0) -> 76.637482
B40: EPS Growth % | D40: =IFERROR(D39/C39-1,0) -> 0.031896149 | E40: =IFERROR(E39/D39-1,0) -> -0.6954095 | F40: =IFERROR(F39/E39-1,0) -> -0.79011124 | G40: =IFERROR(G39/F39-1,0) -> -3.5528471 | H40: =IFERROR(H39/G39-1,0) -> 3.6068468 | I40: =IFERROR(I39/H39-1,0) -> -0.84056344 | J40: =IFERROR(J39/I39-1,0) -> 6.194349 | K40: =IFERROR(K39/J39-1,0) -> -0.70909622 | ... M40: =IFERROR(M39/L39-1,0) -> -0.025334343
B42: Dividend Per Share | C42: =IFERROR('Data Sheet'!B31/'Historical FS'!C36,0) -> 0 | D42: =IFERROR('Data Sheet'!C31/'Historical FS'!D36,0) -> 0.23524522 | E42: =IFERROR('Data Sheet'!D31/'Historical FS'!E36,0) -> 0 | F42: =IFERROR('Data Sheet'!E31/'Historical FS'!F36,0) -> 0 | G42: =IFERROR('Data Sheet'!F31/'Historical FS'!G36,0) -> 0 | H42: =IFERROR('Data Sheet'!G31/'Historical FS'!H36,0) -> 0 | I42: =IFERROR('Data Sheet'!H31/'Historical FS'!I36,0) -> 0 | J42: =IFERROR('Data Sheet'!I31/'Historical FS'!J36,0) -> 0 | ... M42: =IFERROR('Data Sheet'!L31/'Historical FS'!M36,0) -> 0
B43: Dividend Payout Ratio | C43: =IFERROR(C42/C39,0) -> 0 | D43: =IFERROR(D42/D39,0) -> 0.0049323401 | E43: =IFERROR(E42/E39,0) -> 0 | F43: =IFERROR(F42/F39,0) -> 0 | G43: =IFERROR(G42/G39,0) -> 0 | H43: =IFERROR(H42/H39,0) -> 0 | I43: =IFERROR(I42/I39,0) -> 0 | J43: =IFERROR(J42/J39,0) -> 0 | ... M43: =IFERROR(M42/M39,0) -> 0
B45: Retained Earnings | C45: =IFERROR(IF(C39>C42,1-C43,0),0) -> 1 | D45: =IFERROR(IF(D39>D42,1-D43,0),0) -> 0.99506766 | E45: =IFERROR(IF(E39>E42,1-E43,0),0) -> 1 | F45: =IFERROR(IF(F39>F42,1-F43,0),0) -> 1 | G45: =IFERROR(IF(G39>G42,1-G43,0),0) -> 0 | H45: =IFERROR(IF(H39>H42,1-H43,0),0) -> 0 | I45: =IFERROR(IF(I39>I42,1-I43,0),0) -> 0 | J45: =IFERROR(IF(J39>J42,1-J43,0),0) -> 0 | ... M45: =IFERROR(IF(M39>M42,1-M43,0),0) -> 1
A48: # | B48: Balance Sheet | C48: 42094 | D48: 42460 | E48: 42825 | F48: 43190 | G48: 43555 | H48: 43921 | I48: 44286 | J48: 44651 | K48: 45016 | L48: 45382 | M48: LTM
B50: Equity Share Capital | C50: =IFERROR('Data Sheet'!B56,0) -> 643.78 | D50: =IFERROR('Data Sheet'!C56,0) -> 679.18 | E50: =IFERROR('Data Sheet'!D56,0) -> 679.22 | F50: =IFERROR('Data Sheet'!E56,0) -> 679.22 | G50: =IFERROR('Data Sheet'!F56,0) -> 679.22 | H50: =IFERROR('Data Sheet'!G56,0) -> 719.54 | I50: =IFERROR('Data Sheet'!H56,0) -> 765.81 | J50: =IFERROR('Data Sheet'!I56,0) -> 765.88 | ... L50: =IFERROR('Data Sheet'!K56,0) -> 766.5
B51: Reserves | C51: =IFERROR('Data Sheet'!B57,0) -> 55618.14 | D51: =IFERROR('Data Sheet'!C57,0) -> 78273.23 | E51: =IFERROR('Data Sheet'!D57,0) -> 57382.67 | F51: =IFERROR('Data Sheet'!E57,0) -> 94748.69 | G51: =IFERROR('Data Sheet'!F57,0) -> 59500.34 | H51: =IFERROR('Data Sheet'!G57,0) -> 62358.99 | I51: =IFERROR('Data Sheet'!H57,0) -> 54480.91 | J51: =IFERROR('Data Sheet'!I57,0) -> 43795.36 | ... L51: =IFERROR('Data Sheet'!K57,0) -> 84151.52
B52: Borrowings | C52: =IFERROR('Data Sheet'!B58,0) -> 73610.39 | D52: =IFERROR('Data Sheet'!C58,0) -> 69359.96 | E52: =IFERROR('Data Sheet'!D58,0) -> 78603.98 | F52: =IFERROR('Data Sheet'!E58,0) -> 88950.47 | G52: =IFERROR('Data Sheet'!F58,0) -> 106175.34 | H52: =IFERROR('Data Sheet'!G58,0) -> 124787.64 | I52: =IFERROR('Data Sheet'!H58,0) -> 142130.57 | J52: =IFERROR('Data Sheet'!I58,0) -> 146449.03 | ... L52: =IFERROR('Data Sheet'!K58,0) -> 107262.5
B53: Other Liabilities | C53: =IFERROR('Data Sheet'!B59,0) -> 107442.48 | D53: =IFERROR('Data Sheet'!C59,0) -> 114871.75 | E53: =IFERROR('Data Sheet'!D59,0) -> 135914.49 | F53: =IFERROR('Data Sheet'!E59,0) -> 142813.43 | G53: =IFERROR('Data Sheet'!F59,0) -> 139348.59 | H53: =IFERROR('Data Sheet'!G59,0) -> 132313.22 | I53: =IFERROR('Data Sheet'!H59,0) -> 144192.62 | J53: =IFERROR('Data Sheet'!I59,0) -> 138051.22 | ... L53: =IFERROR('Data Sheet'!K59,0) -> 177340.09
B54: Total Liabilities | C54: =IFERROR('Data Sheet'!B60,0) -> 237314.79 | D54: =IFERROR('Data Sheet'!C60,0) -> 263184.12 | E54: =IFERROR('Data Sheet'!D60,0) -> 272580.36 | F54: =IFERROR('Data Sheet'!E60,0) -> 327191.81 | G54: =IFERROR('Data Sheet'!F60,0) -> 305703.49 | H54: =IFERROR('Data Sheet'!G60,0) -> 320179.39 | I54: =IFERROR('Data Sheet'!H60,0) -> 341569.91 | J54: =IFERROR('Data Sheet'!I60,0) -> 329061.49 | ... L54: =IFERROR('Data Sheet'!K60,0) -> 369520.61
B56: Fixed Assets Net Block | C56: =IFERROR('Data Sheet'!B61,0) -> 88479.49 | D56: =IFERROR('Data Sheet'!C61,0) -> 107231.76 | E56: =IFERROR('Data Sheet'!D61,0) -> 95944.08 | F56: =IFERROR('Data Sheet'!E61,0) -> 121413.86 | G56: =IFERROR('Data Sheet'!F61,0) -> 111234.47 | H56: =IFERROR('Data Sheet'!G61,0) -> 127107.14 | I56: =IFERROR('Data Sheet'!H61,0) -> 138707.61 | J56: =IFERROR('Data Sheet'!I61,0) -> 138855.45 | ... L56: =IFERROR('Data Sheet'!K61,0) -> 121285.46
B57: Capital Work in Progress | C57: =IFERROR('Data Sheet'!B62,0) -> 28640.09 | D57: =IFERROR('Data Sheet'!C62,0) -> 25918.94 | E57: =IFERROR('Data Sheet'!D62,0) -> 33698.84 | F57: =IFERROR('Data Sheet'!E62,0) -> 40033.5 | G57: =IFERROR('Data Sheet'!F62,0) -> 31883.84 | H57: =IFERROR('Data Sheet'!G62,0) -> 35622.29 | I57: =IFERROR('Data Sheet'!H62,0) -> 20963.93 | J57: =IFERROR('Data Sheet'!I62,0) -> 10251.09 | ... L57: =IFERROR('Data Sheet'!K62,0) -> 35698.43
B58: Investments | C58: =IFERROR('Data Sheet'!B63,0) -> 15336.74 | D58: =IFERROR('Data Sheet'!C63,0) -> 23767.02 | E58: =IFERROR('Data Sheet'!D63,0) -> 20337.92 | F58: =IFERROR('Data Sheet'!E63,0) -> 20812.75 | G58: =IFERROR('Data Sheet'!F63,0) -> 15770.72 | H58: =IFERROR('Data Sheet'!G63,0) -> 16308.48 | I58: =IFERROR('Data Sheet'!H63,0) -> 24620.28 | J58: =IFERROR('Data Sheet'!I63,0) -> 29379.53 | ... L58: =IFERROR('Data Sheet'!K63,0) -> 22971.07
B59: Other Assets | C59: =IFERROR('Data Sheet'!B64-SUM('Data Sheet'!B66:B68),0) -> 30891.17 | D59: =IFERROR('Data Sheet'!C64-SUM('Data Sheet'!C66:C68),0) -> 29579.36 | E59: =IFERROR('Data Sheet'!D64-SUM('Data Sheet'!D66:D68),0) -> 37360.78 | F59: =IFERROR('Data Sheet'!E64-SUM('Data Sheet'!E66:E68),0) -> 48286.86 | G59: =IFERROR('Data Sheet'!F64-SUM('Data Sheet'!F66:F68),0) -> 56155.74 | H59: =IFERROR('Data Sheet'!G64-SUM('Data Sheet'!G66:G68),0) -> 58784.94 | I59: =IFERROR('Data Sheet'!H64-SUM('Data Sheet'!H66:H68),0) -> 61717.96 | J59: =IFERROR('Data Sheet'!I64-SUM('Data Sheet'!I66:I68),0) -> 62223.77 | ... L59: =IFERROR('Data Sheet'!K64-SUM('Data Sheet'!K66:K68),0) -> 79018.86
B60: Total Non-Current Assets | C60: =IFERROR(SUM(C56:C59),0) -> 163347.49 | D60: =IFERROR(SUM(D56:D59),0) -> 186497.08 | E60: =IFERROR(SUM(E56:E59),0) -> 187341.62 | F60: =IFERROR(SUM(F56:F59),0) -> 230546.97 | G60: =IFERROR(SUM(G56:G59),0) -> 215044.77 | H60: =IFERROR(SUM(H56:H59),0) -> 237822.85 | I60: =IFERROR(SUM(I56:I59),0) -> 246009.78 | J60: =IFERROR(SUM(J56:J59),0) -> 240709.84 | ... L60: =IFERROR(SUM(L56:L59),0) -> 258973.82
B62: Receivables | C62: =IFERROR('Data Sheet'!B66,0) -> 12579.2 | D62: =IFERROR('Data Sheet'!C66,0) -> 13570.91 | E62: =IFERROR('Data Sheet'!D66,0) -> 14075.55 | F62: =IFERROR('Data Sheet'!E66,0) -> 19893.3 | G62: =IFERROR('Data Sheet'!F66,0) -> 18996.17 | H62: =IFERROR('Data Sheet'!G66,0) -> 11172.69 | I62: =IFERROR('Data Sheet'!H66,0) -> 12679.08 | J62: =IFERROR('Data Sheet'!I66,0) -> 12442.12 | ... L62: =IFERROR('Data Sheet'!K66,0) -> 16951.81
B63: Inventory | C63: =IFERROR('Data Sheet'!B67,0) -> 29272.34 | D63: =IFERROR('Data Sheet'!C67,0) -> 32655.73 | E63: =IFERROR('Data Sheet'!D67,0) -> 35085.31 | F63: =IFERROR('Data Sheet'!E67,0) -> 42137.63 | G63: =IFERROR('Data Sheet'!F67,0) -> 39013.73 | H63: =IFERROR('Data Sheet'!G67,0) -> 37456.88 | I63: =IFERROR('Data Sheet'!H67,0) -> 36088.59 | J63: =IFERROR('Data Sheet'!I67,0) -> 35240.34 | ... L63: =IFERROR('Data Sheet'!K67,0) -> 47788.29
B64: Cash & Bank | C64: =IFERROR('Data Sheet'!B68,0) -> 32115.76 | D64: =IFERROR('Data Sheet'!C68,0) -> 30460.4 | E64: =IFERROR('Data Sheet'!D68,0) -> 36077.88 | F64: =IFERROR('Data Sheet'!E68,0) -> 34613.91 | G64: =IFERROR('Data Sheet'!F68,0) -> 32648.82 | H64: =IFERROR('Data Sheet'!G68,0) -> 33726.97 | I64: =IFERROR('Data Sheet'!H68,0) -> 46792.46 | J64: =IFERROR('Data Sheet'!I68,0) -> 40669.19 | ... L64: =IFERROR('Data Sheet'!K68,0) -> 45806.69
B65: Total Current Assets | C65: =IFERROR(SUM(C62:C64),0) -> 73967.3 | D65: =IFERROR(SUM(D62:D64),0) -> 76687.04 | E65: =IFERROR(SUM(E62:E64),0) -> 85238.74 | F65: =IFERROR(SUM(F62:F64),0) -> 96644.84 | G65: =IFERROR(SUM(G62:G64),0) -> 90658.72 | H65: =IFERROR(SUM(H62:H64),0) -> 82356.54 | I65: =IFERROR(SUM(I62:I64),0) -> 95560.13 | J65: =IFERROR(SUM(J62:J64),0) -> 88351.65 | ... L65: =IFERROR(SUM(L62:L64),0) -> 110546.79
B67: Total Assets | C67: =IFERROR(SUM(C60,C65),0) -> 237314.79 | D67: =IFERROR(SUM(D60,D65),0) -> 263184.12 | E67: =IFERROR(SUM(E60,E65),0) -> 272580.36 | F67: =IFERROR(SUM(F60,F65),0) -> 327191.81 | G67: =IFERROR(SUM(G60,G65),0) -> 305703.49 | H67: =IFERROR(SUM(H60,H65),0) -> 320179.39 | I67: =IFERROR(SUM(I60,I65),0) -> 341569.91 | J67: =IFERROR(SUM(J60,J65),0) -> 329061.49 | ... L67: =IFERROR(SUM(L60,L65),0) -> 369520.61
B69: Check | C69: =C54=C67 -> TRUE | D69: =D54=D67 -> TRUE | E69: =E54=E67 -> TRUE | F69: =F54=F67 -> TRUE | G69: =G54=G67 -> TRUE | H69: =H54=H67 -> TRUE | I69: =I54=I67 -> TRUE | J69: =J54=J67 -> TRUE | ... L69: =L54=L67 -> TRUE
A71: # | B71: Cash Flow Statements | C71: 42094 | D71: 42460 | E71: 42825 | F71: 43190 | G71: 43555 | H71: 43921 | I71: 44286 | J71: 44651 | K71: 45016 | L71: 45382 | M71: LTM
B72: Operating Activities
B73: Profit from operations | C73: =IFERROR('Cash Flow Data'!C4,0) -> 43397 | D73: =IFERROR('Cash Flow Data'!D4,0) -> 38626 | E73: =IFERROR('Cash Flow Data'!E4,0) -> 28840 | F73: =IFERROR('Cash Flow Data'!F4,0) -> 33312 | G73: =IFERROR('Cash Flow Data'!G4,0) -> 28771 | H73: =IFERROR('Cash Flow Data'!H4,0) -> 23352 | I73: =IFERROR('Cash Flow Data'!I4,0) -> 31198 | J73: =IFERROR('Cash Flow Data'!J4,0) -> 26943 | ... L73: =IFERROR('Cash Flow Data'!L4,0) -> 65106
B74: Receivables | C74: =IFERROR('Cash Flow Data'!C5,0) -> -3179 | D74: =IFERROR('Cash Flow Data'!D5,0) -> -2223 | E74: =IFERROR('Cash Flow Data'!E5,0) -> -4152 | F74: =IFERROR('Cash Flow Data'!F5,0) -> -10688 | G74: =IFERROR('Cash Flow Data'!G5,0) -> -9109 | H74: =IFERROR('Cash Flow Data'!H5,0) -> 9950 | I74: =IFERROR('Cash Flow Data'!I5,0) -> -5505 | J74: =IFERROR('Cash Flow Data'!J5,0) -> 185 | ... L74: =IFERROR('Cash Flow Data'!L5,0) -> -1875
B75: Inventory | C75: =IFERROR('Cash Flow Data'!C6,0) -> -3692 | D75: =IFERROR('Cash Flow Data'!D6,0) -> -5743 | E75: =IFERROR('Cash Flow Data'!E6,0) -> -6621 | F75: =IFERROR('Cash Flow Data'!F6,0) -> -3560 | G75: =IFERROR('Cash Flow Data'!G6,0) -> 2069 | H75: =IFERROR('Cash Flow Data'!H6,0) -> 2326 | I75: =IFERROR('Cash Flow Data'!I6,0) -> 3814 | J75: =IFERROR('Cash Flow Data'!J6,0) -> 472 | ... L75: =IFERROR('Cash Flow Data'!L6,0) -> -7265
B76: Payables | C76: =IFERROR('Cash Flow Data'!C7,0) -> 3598 | D76: =IFERROR('Cash Flow Data'!D7,0) -> 3947 | E76: =IFERROR('Cash Flow Data'!E7,0) -> 9301 | F76: =IFERROR('Cash Flow Data'!F7,0) -> 7320 | G76: =IFERROR('Cash Flow Data'!G7,0) -> -4692 | H76: =IFERROR('Cash Flow Data'!H7,0) -> -8085 | I76: =IFERROR('Cash Flow Data'!I7,0) -> 5748 | J76: =IFERROR('Cash Flow Data'!J7,0) -> -7012 | ... L76: =IFERROR('Cash Flow Data'!L7,0) -> 13706
B77: Loans Advances | C77: =IFERROR('Cash Flow Data'!C8,0) -> 0 | D77: =IFERROR('Cash Flow Data'!D8,0) -> -520 | E77: =IFERROR('Cash Flow Data'!E8,0) -> 0 | F77: =IFERROR('Cash Flow Data'!F8,0) -> 0 | G77: =IFERROR('Cash Flow Data'!G8,0) -> 0 | H77: =IFERROR('Cash Flow Data'!H8,0) -> 0 | I77: =IFERROR('Cash Flow Data'!I8,0) -> 0 | J77: =IFERROR('Cash Flow Data'!J8,0) -> 0 | ... L77: =IFERROR('Cash Flow Data'!L8,0) -> 0
B78: Other WC items | C78: =IFERROR('Cash Flow Data'!C9,0) -> -398 | D78: =IFERROR('Cash Flow Data'!D9,0) -> 5852 | E78: =IFERROR('Cash Flow Data'!E9,0) -> 4727 | F78: =IFERROR('Cash Flow Data'!F9,0) -> 494 | G78: =IFERROR('Cash Flow Data'!G9,0) -> 4512 | H78: =IFERROR('Cash Flow Data'!H9,0) -> 875 | I78: =IFERROR('Cash Flow Data'!I9,0) -> -4150 | J78: =IFERROR('Cash Flow Data'!J9,0) -> -4396 | ... L78: =IFERROR('Cash Flow Data'!L9,0) -> 2760
B79: Working capital changes | C79: =IFERROR('Cash Flow Data'!C10,0) -> -3672 | D79: =IFERROR('Cash Flow Data'!D10,0) -> 1313 | E79: =IFERROR('Cash Flow Data'!E10,0) -> 3254 | F79: =IFERROR('Cash Flow Data'!F10,0) -> -6434 | G79: =IFERROR('Cash Flow Data'!G10,0) -> -7221 | H79: =IFERROR('Cash Flow Data'!H10,0) -> 5065 | I79: =IFERROR('Cash Flow Data'!I10,0) -> -93 | J79: =IFERROR('Cash Flow Data'!J10,0) -> -10750 | ... L79: =IFERROR('Cash Flow Data'!L10,0) -> 7325
B80: Direct taxes | C80: =IFERROR('Cash Flow Data'!C11,0) -> -4194 | D80: =IFERROR('Cash Flow Data'!D11,0) -> -2040 | E80: =IFERROR('Cash Flow Data'!E11,0) -> -1895 | F80: =IFERROR('Cash Flow Data'!F11,0) -> -3021 | G80: =IFERROR('Cash Flow Data'!G11,0) -> -2659 | H80: =IFERROR('Cash Flow Data'!H11,0) -> -1785 | I80: =IFERROR('Cash Flow Data'!I11,0) -> -2105 | J80: =IFERROR('Cash Flow Data'!J11,0) -> -1910 | ... L80: =IFERROR('Cash Flow Data'!L11,0) -> -4516
B81: Cash Flow from Operating Activities | C81: =IFERROR(SUM(C73:C80),0) -> 31860 | D81: =IFERROR(SUM(D73:D80),0) -> 39212 | E81: =IFERROR(SUM(E73:E80),0) -> 33454 | F81: =IFERROR(SUM(F73:F80),0) -> 17423 | G81: =IFERROR(SUM(G73:G80),0) -> 11671 | H81: =IFERROR(SUM(H73:H80),0) -> 31698 | I81: =IFERROR(SUM(I73:I80),0) -> 28907 | J81: =IFERROR(SUM(J73:J80),0) -> 3532 | ... L81: =IFERROR(SUM(L73:L80),0) -> 75241
B83: Investing Activities
B84: Fixed assets purchased | C84: =IFERROR('Cash Flow Data'!C13,0) -> -31962 | D84: =IFERROR('Cash Flow Data'!D13,0) -> -31503 | E84: =IFERROR('Cash Flow Data'!E13,0) -> -16072 | F84: =IFERROR('Cash Flow Data'!F13,0) -> -35079 | G84: =IFERROR('Cash Flow Data'!G13,0) -> -35304 | H84: =IFERROR('Cash Flow Data'!H13,0) -> -29702 | I84: =IFERROR('Cash Flow Data'!I13,0) -> -20205 | J84: =IFERROR('Cash Flow Data'!J13,0) -> -15168 | ... L84: =IFERROR('Cash Flow Data'!L13,0) -> -31414
B85: Fixed assets sold | C85: =IFERROR('Cash Flow Data'!C14,0) -> 74 | D85: =IFERROR('Cash Flow Data'!D14,0) -> 59 | E85: =IFERROR('Cash Flow Data'!E14,0) -> 53 | F85: =IFERROR('Cash Flow Data'!F14,0) -> 30 | G85: =IFERROR('Cash Flow Data'!G14,0) -> 67 | H85: =IFERROR('Cash Flow Data'!H14,0) -> 171 | I85: =IFERROR('Cash Flow Data'!I14,0) -> 351 | J85: =IFERROR('Cash Flow Data'!J14,0) -> 230 | ... L85: =IFERROR('Cash Flow Data'!L14,0) -> 231
B86: Investments purchased | C86: =IFERROR('Cash Flow Data'!C15,0) -> -5461 | D86: =IFERROR('Cash Flow Data'!D15,0) -> -4728 | E86: =IFERROR('Cash Flow Data'!E15,0) -> -6 | F86: =IFERROR('Cash Flow Data'!F15,0) -> -329 | G86: =IFERROR('Cash Flow Data'!G15,0) -> -130 | H86: =IFERROR('Cash Flow Data'!H15,0) -> -1439 | I86: =IFERROR('Cash Flow Data'!I15,0) -> -7530 | J86: =IFERROR('Cash Flow Data'!J15,0) -> -3008 | ... L86: =IFERROR('Cash Flow Data'!L15,0) -> -74
B87: Investments sold | C87: =IFERROR('Cash Flow Data'!C16,0) -> 42 | D87: =IFERROR('Cash Flow Data'!D16,0) -> 89 | E87: =IFERROR('Cash Flow Data'!E16,0) -> 1965 | F87: =IFERROR('Cash Flow Data'!F16,0) -> 2381 | G87: =IFERROR('Cash Flow Data'!G16,0) -> 5644 | H87: =IFERROR('Cash Flow Data'!H16,0) -> 21 | I87: =IFERROR('Cash Flow Data'!I16,0) -> 226 | J87: =IFERROR('Cash Flow Data'!J16,0) -> 104 | ... L87: =IFERROR('Cash Flow Data'!L16,0) -> 10820
B88: Interest received | C88: =IFERROR('Cash Flow Data'!C17,0) -> 698 | D88: =IFERROR('Cash Flow Data'!D17,0) -> 731 | E88: =IFERROR('Cash Flow Data'!E17,0) -> 638 | F88: =IFERROR('Cash Flow Data'!F17,0) -> 690 | G88: =IFERROR('Cash Flow Data'!G17,0) -> 761 | H88: =IFERROR('Cash Flow Data'!H17,0) -> 1104 | I88: =IFERROR('Cash Flow Data'!I17,0) -> 428 | J88: =IFERROR('Cash Flow Data'!J17,0) -> 653 | ... L88: =IFERROR('Cash Flow Data'!L17,0) -> 2493
B89: Dividends received | C89: =IFERROR('Cash Flow Data'!C18,0) -> 80 | D89: =IFERROR('Cash Flow Data'!D18,0) -> 58 | E89: =IFERROR('Cash Flow Data'!E18,0) -> 620 | F89: =IFERROR('Cash Flow Data'!F18,0) -> 1797 | G89: =IFERROR('Cash Flow Data'!G18,0) -> 232 | H89: =IFERROR('Cash Flow Data'!H18,0) -> 21 | I89: =IFERROR('Cash Flow Data'!I18,0) -> 18 | J89: =IFERROR('Cash Flow Data'!J18,0) -> 32 | ... L89: =IFERROR('Cash Flow Data'!L18,0) -> 47
B90: Investment in group cos | C90: =IFERROR('Cash Flow Data'!C19,0) -> -160 | D90: =IFERROR('Cash Flow Data'!D19,0) -> 0 | E90: =IFERROR('Cash Flow Data'!E19,0) -> -107 | F90: =IFERROR('Cash Flow Data'!F19,0) -> -4 | G90: =IFERROR('Cash Flow Data'!G19,0) -> -9 | H90: =IFERROR('Cash Flow Data'!H19,0) -> -606 | I90: =IFERROR('Cash Flow Data'!I19,0) -> -10 | J90: =IFERROR('Cash Flow Data'!J19,0) -> 0 | ... L90: =IFERROR('Cash Flow Data'!L19,0) -> -150
B91: Redemp n Canc of Shares | C91: =IFERROR('Cash Flow Data'!C20,0) -> 0 | D91: =IFERROR('Cash Flow Data'!D20,0) -> 0 | E91: =IFERROR('Cash Flow Data'!E20,0) -> 0 | F91: =IFERROR('Cash Flow Data'!F20,0) -> 14 | G91: =IFERROR('Cash Flow Data'!G20,0) -> 533 | H91: =IFERROR('Cash Flow Data'!H20,0) -> 0 | I91: =IFERROR('Cash Flow Data'!I20,0) -> 0 | J91: =IFERROR('Cash Flow Data'!J20,0) -> 0 | ... L91: =IFERROR('Cash Flow Data'!L20,0) -> 108
B92: Acquisition of companies | C92: =IFERROR('Cash Flow Data'!C21,0) -> 0 | D92: =IFERROR('Cash Flow Data'!D21,0) -> -111 | E92: =IFERROR('Cash Flow Data'!E21,0) -> 0 | F92: =IFERROR('Cash Flow Data'!F21,0) -> 0 | G92: =IFERROR('Cash Flow Data'!G21,0) -> -8 | H92: =IFERROR('Cash Flow Data'!H21,0) -> -27 | I92: =IFERROR('Cash Flow Data'!I21,0) -> 0 | J92: =IFERROR('Cash Flow Data'!J21,0) -> -98 | ... L92: =IFERROR('Cash Flow Data'!L21,0) -> 0
B93: Inter corporate deposits | C93: =IFERROR('Cash Flow Data'!C22,0) -> 0 | D93: =IFERROR('Cash Flow Data'!D22,0) -> 0 | E93: =IFERROR('Cash Flow Data'!E22,0) -> 0 | F93: =IFERROR('Cash Flow Data'!F22,0) -> 0 | G93: =IFERROR('Cash Flow Data'!G22,0) -> 0 | H93: =IFERROR('Cash Flow Data'!H22,0) -> 0 | I93: =IFERROR('Cash Flow Data'!I22,0) -> 0 | J93: =IFERROR('Cash Flow Data'!J22,0) -> 0 | ... L93: =IFERROR('Cash Flow Data'!L22,0) -> -24
B94: Other investing items | C94: =IFERROR('Cash Flow Data'!C23,0) -> 456 | D94: =IFERROR('Cash Flow Data'!D23,0) -> -1289 | E94: =IFERROR('Cash Flow Data'!E23,0) -> -26663 | F94: =IFERROR('Cash Flow Data'!F23,0) -> 5360 | G94: =IFERROR('Cash Flow Data'!G23,0) -> 7335 | H94: =IFERROR('Cash Flow Data'!H23,0) -> -2659 | I94: =IFERROR('Cash Flow Data'!I23,0) -> 1051 | J94: =IFERROR('Cash Flow Data'!J23,0) -> 12813 | ... L94: =IFERROR('Cash Flow Data'!L23,0) -> -4817
B95: Cash Flow from Investing Activities | C95: =IFERROR(SUM(C84:C94),0) -> -36233 | D95: =IFERROR(SUM(D84:D94),0) -> -36694 | E95: =IFERROR(SUM(E84:E94),0) -> -39572 | F95: =IFERROR(SUM(F84:F94),0) -> -25140 | G95: =IFERROR(SUM(G84:G94),0) -> -20879 | H95: =IFERROR(SUM(H84:H94),0) -> -33116 | I95: =IFERROR(SUM(I84:I94),0) -> -25671 | J95: =IFERROR(SUM(J84:J94),0) -> -4442 | ... L95: =IFERROR(SUM(L84:L94),0) -> -22780
B97: Financing Activities
B98: Proceeds from shares | C98: =IFERROR('Cash Flow Data'!C25,0) -> 0 | D98: =IFERROR('Cash Flow Data'!D25,0) -> 7433 | E98: =IFERROR('Cash Flow Data'!E25,0) -> 5 | F98: =IFERROR('Cash Flow Data'!F25,0) -> 0 | G98: =IFERROR('Cash Flow Data'!G25,0) -> 0 | H98: =IFERROR('Cash Flow Data'!H25,0) -> 3889 | I98: =IFERROR('Cash Flow Data'!I25,0) -> 2603 | J98: =IFERROR('Cash Flow Data'!J25,0) -> 19 | ... L98: =IFERROR('Cash Flow Data'!L25,0) -> 82
B99: Redemption of debentures | C99: =IFERROR('Cash Flow Data'!C26,0) -> -744 | D99: =IFERROR('Cash Flow Data'!D26,0) -> 0 | E99: =IFERROR('Cash Flow Data'!E26,0) -> 0 | F99: =IFERROR('Cash Flow Data'!F26,0) -> 0 | G99: =IFERROR('Cash Flow Data'!G26,0) -> 0 | H99: =IFERROR('Cash Flow Data'!H26,0) -> 0 | I99: =IFERROR('Cash Flow Data'!I26,0) -> 0 | J99: =IFERROR('Cash Flow Data'!J26,0) -> 0 | ... L99: =IFERROR('Cash Flow Data'!L26,0) -> 0
B100: Proceeds from borrowings | C100: =IFERROR('Cash Flow Data'!C27,0) -> 36363 | D100: =IFERROR('Cash Flow Data'!D27,0) -> 19519 | E100: =IFERROR('Cash Flow Data'!E27,0) -> 33390 | F100: =IFERROR('Cash Flow Data'!F27,0) -> 37482 | G100: =IFERROR('Cash Flow Data'!G27,0) -> 51128 | H100: =IFERROR('Cash Flow Data'!H27,0) -> 38297 | I100: =IFERROR('Cash Flow Data'!I27,0) -> 46641 | J100: =IFERROR('Cash Flow Data'!J27,0) -> 46578 | ... L100: =IFERROR('Cash Flow Data'!L27,0) -> 18747
B101: Repayment of borrowings | C101: =IFERROR('Cash Flow Data'!C28,0) -> -23332 | D101: =IFERROR('Cash Flow Data'!D28,0) -> -24924 | E101: =IFERROR('Cash Flow Data'!E28,0) -> -21732 | F101: =IFERROR('Cash Flow Data'!F28,0) -> -29964 | G101: =IFERROR('Cash Flow Data'!G28,0) -> -35198 | H101: =IFERROR('Cash Flow Data'!H28,0) -> -29847 | I101: =IFERROR('Cash Flow Data'!I28,0) -> -29709 | J101: =IFERROR('Cash Flow Data'!J28,0) -> -42816 | ... L101: =IFERROR('Cash Flow Data'!L28,0) -> -47332
B102: Interest paid fin | C102: =IFERROR('Cash Flow Data'!C29,0) -> -6307 | D102: =IFERROR('Cash Flow Data'!D29,0) -> -5716 | E102: =IFERROR('Cash Flow Data'!E29,0) -> -5336 | F102: =IFERROR('Cash Flow Data'!F29,0) -> -5411 | G102: =IFERROR('Cash Flow Data'!G29,0) -> -7005 | H102: =IFERROR('Cash Flow Data'!H29,0) -> -7518 | I102: =IFERROR('Cash Flow Data'!I29,0) -> -8123 | J102: =IFERROR('Cash Flow Data'!J29,0) -> -9251 | ... L102: =IFERROR('Cash Flow Data'!L29,0) -> -9332
B103: Dividends paid | C103: =IFERROR('Cash Flow Data'!C30,0) -> -720 | D103: =IFERROR('Cash Flow Data'!D30,0) -> -108 | E103: =IFERROR('Cash Flow Data'!E30,0) -> -121 | F103: =IFERROR('Cash Flow Data'!F30,0) -> -96 | G103: =IFERROR('Cash Flow Data'!G30,0) -> -95 | H103: =IFERROR('Cash Flow Data'!H30,0) -> -57 | I103: =IFERROR('Cash Flow Data'!I30,0) -> -30 | J103: =IFERROR('Cash Flow Data'!J30,0) -> -100 | ... L103: =IFERROR('Cash Flow Data'!L30,0) -> -1059
B104: Financial liabilities | C104: =IFERROR('Cash Flow Data'!C31,0) -> 0 | D104: =IFERROR('Cash Flow Data'!D31,0) -> 0 | E104: =IFERROR('Cash Flow Data'!E31,0) -> 0 | F104: =IFERROR('Cash Flow Data'!F31,0) -> 0 | G104: =IFERROR('Cash Flow Data'!G31,0) -> 0 | H104: =IFERROR('Cash Flow Data'!H31,0) -> -1346 | I104: =IFERROR('Cash Flow Data'!I31,0) -> -1477 | J104: =IFERROR('Cash Flow Data'!J31,0) -> -1559 | ... L104: =IFERROR('Cash Flow Data'!L31,0) -> -1924
B105: Other financing items | C105: =IFERROR('Cash Flow Data'!C32,0) -> -57 | D105: =IFERROR('Cash Flow Data'!D32,0) -> 0 | E105: =IFERROR('Cash Flow Data'!E32,0) -> 0 | F105: =IFERROR('Cash Flow Data'!F32,0) -> 0 | G105: =IFERROR('Cash Flow Data'!G32,0) -> 0 | H105: =IFERROR('Cash Flow Data'!H32,0) -> -29 | I105: =IFERROR('Cash Flow Data'!I32,0) -> 0 | J105: =IFERROR('Cash Flow Data'!J32,0) -> 3750 | ... L105: =IFERROR('Cash Flow Data'!L32,0) -> 3812
B106: Cash Flow from Financing Activities | C106: =IFERROR(SUM(C98:C105),0) -> 5203 | D106: =IFERROR(SUM(D98:D105),0) -> -3796 | E106: =IFERROR(SUM(E98:E105),0) -> 6206 | F106: =IFERROR(SUM(F98:F105),0) -> 2011 | G106: =IFERROR(SUM(G98:G105),0) -> 8830 | H106: =IFERROR(SUM(H98:H105),0) -> 3389 | I106: =IFERROR(SUM(I98:I105),0) -> 9905 | J106: =IFERROR(SUM(J98:J105),0) -> -3379 | ... L106: =IFERROR(SUM(L98:L105),0) -> -37006
B108: Net Cash Flow | C108: =IFERROR(C81+C95+C106,0) -> 830 | D108: =IFERROR(D81+D95+D106,0) -> -1278 | E108: =IFERROR(E81+E95+E106,0) -> 88 | F108: =IFERROR(F81+F95+F106,0) -> -5706 | G108: =IFERROR(G81+G95+G106,0) -> -378 | H108: =IFERROR(H81+H95+H106,0) -> 1971 | I108: =IFERROR(I81+I95+I106,0) -> 13141 | J108: =IFERROR(J81+J95+J106,0) -> -4289 | ... L108: =IFERROR(L81+L95+L106,0) -> 15455

Sheet Common Size Analysis
B2: ="Common Size Financial Statement Analysis"&" - "&'Data Sheet'!B1 -> Common Size Financial Statement Analysis - TATA MOTORS LTD
A4: # | B4: Common Size Balance Sheet
B6: Particulars | C6: ='Data Sheet'!B55 -> 42094 | D6: ='Data Sheet'!C55 -> 42460 | E6: ='Data Sheet'!D55 -> 42825 | F6: ='Data Sheet'!E55 -> 43190 | G6: ='Data Sheet'!F55 -> 43555 | H6: ='Data Sheet'!G55 -> 43921 | I6: ='Data Sheet'!H55 -> 44286 | J6: ='Data Sheet'!I55 -> 44651 | ... L6: ='Data Sheet'!K55 -> 45382
B8: Equity Share Capital | C8: ='Data Sheet'!B56/'Data Sheet'!B$60 -> 0.0027127681 | D8: ='Data Sheet'!C56/'Data Sheet'!C$60 -> 0.0025806268 | E8: ='Data Sheet'!D56/'Data Sheet'!D$60 -> 0.0024918156 | F8: ='Data Sheet'!E56/'Data Sheet'!E$60 -> 0.0020759077 | G8: ='Data Sheet'!F56/'Data Sheet'!F$60 -> 0.0022218261 | H8: ='Data Sheet'!G56/'Data Sheet'!G$60 -> 0.0022473027 | I8: ='Data Sheet'!H56/'Data Sheet'!H$60 -> 0.00224203 | J8: ='Data Sheet'!I56/'Data Sheet'!I$60 -> 0.0023274677 | ... L8: ='Data Sheet'!K56/'Data Sheet'!K$60 -> 0.0020743092
B9: Reserves | C9: ='Data Sheet'!B57/'Data Sheet'!B$60 -> 0.23436441 | D9: ='Data Sheet'!C57/'Data Sheet'!C$60 -> 0.29740864 | E9: ='Data Sheet'!D57/'Data Sheet'!D$60 -> 0.21051652 | F9: ='Data Sheet'!E57/'Data Sheet'!E$60 -> 0.28958148 | G9: ='Data Sheet'!F57/'Data Sheet'!F$60 -> 0.19463415 | H9: ='Data Sheet'!G57/'Data Sheet'!G$60 -> 0.19476266 | I9: ='Data Sheet'!H57/'Data Sheet'!H$60 -> 0.15950149 | J9: ='Data Sheet'!I57/'Data Sheet'!I$60 -> 0.13309172 | ... L9: ='Data Sheet'!K57/'Data Sheet'!K$60 -> 0.2277316
B10: Borrowings | C10: ='Data Sheet'!B58/'Data Sheet'!B$60 -> 0.31018037 | D10: ='Data Sheet'!C58/'Data Sheet'!C$60 -> 0.26354158 | E10: ='Data Sheet'!D58/'Data Sheet'!D$60 -> 0.28836993 | F10: ='Data Sheet'!E58/'Data Sheet'!E$60 -> 0.27186032 | G10: ='Data Sheet'!F58/'Data Sheet'!F$60 -> 0.34731478 | H10: ='Data Sheet'!G58/'Data Sheet'!G$60 -> 0.38974289 | I10: ='Data Sheet'!H58/'Data Sheet'!H$60 -> 0.41610975 | J10: ='Data Sheet'!I58/'Data Sheet'!I$60 -> 0.44505065 | ... L10: ='Data Sheet'!K58/'Data Sheet'!K$60 -> 0.29027474
B11: Other Liabilities | C11: ='Data Sheet'!B59/'Data Sheet'!B$60 -> 0.45274245 | D11: ='Data Sheet'!C59/'Data Sheet'!C$60 -> 0.43646915 | E11: ='Data Sheet'!D59/'Data Sheet'!D$60 -> 0.49862173 | F11: ='Data Sheet'!E59/'Data Sheet'!E$60 -> 0.43648229 | G11: ='Data Sheet'!F59/'Data Sheet'!F$60 -> 0.45582924 | H11: ='Data Sheet'!G59/'Data Sheet'!G$60 -> 0.41324715 | I11: ='Data Sheet'!H59/'Data Sheet'!H$60 -> 0.42214673 | J11: ='Data Sheet'!I59/'Data Sheet'!I$60 -> 0.41953016 | ... L11: ='Data Sheet'!K59/'Data Sheet'!K$60 -> 0.47991935
B12: Total Liabilities | C12: =SUM(C8:C11) -> 1 | D12: =SUM(D8:D11) -> 1 | E12: =SUM(E8:E11) -> 1 | F12: =SUM(F8:F11) -> 1 | G12: =SUM(G8:G11) -> 1 | H12: =SUM(H8:H11) -> 1 | I12: =SUM(I8:I11) -> 1 | J12: =SUM(J8:J11) -> 1 | ... L12: =SUM(L8:L11) -> 1
B14: Net Block | C14: ='Data Sheet'!B61/'Data Sheet'!B$65 -> 0.37283597 | D14: ='Data Sheet'!C61/'Data Sheet'!C$65 -> 0.40744008 | E14: ='Data Sheet'!D61/'Data Sheet'!D$65 -> 0.35198457 | F14: ='Data Sheet'!E61/'Data Sheet'!E$65 -> 0.37107854 | G14: ='Data Sheet'!F61/'Data Sheet'!F$65 -> 0.36386392 | H14: ='Data Sheet'!G61/'Data Sheet'!G$65 -> 0.39698726 | I14: ='Data Sheet'!H61/'Data Sheet'!H$65 -> 0.40608849 | J14: ='Data Sheet'!I61/'Data Sheet'!I$65 -> 0.42197417 | ... L14: ='Data Sheet'!K61/'Data Sheet'!K$65 -> 0.3282238
B15: Capital Work in Progress | C15: ='Data Sheet'!B62/'Data Sheet'!B$65 -> 0.12068397 | D15: ='Data Sheet'!C62/'Data Sheet'!C$65 -> 0.098482158 | E15: ='Data Sheet'!D62/'Data Sheet'!D$65 -> 0.12362901 | F15: ='Data Sheet'!E62/'Data Sheet'!E$65 -> 0.12235484 | G15: ='Data Sheet'!F62/'Data Sheet'!F$65 -> 0.10429662 | H15: ='Data Sheet'!G62/'Data Sheet'!G$65 -> 0.11125729 | I15: ='Data Sheet'!H62/'Data Sheet'!H$65 -> 0.061375225 | J15: ='Data Sheet'!I62/'Data Sheet'!I$65 -> 0.031152506 | ... L15: ='Data Sheet'!K62/'Data Sheet'!K$65 -> 0.096607413
B16: Investments | C16: ='Data Sheet'!B63/'Data Sheet'!B$65 -> 0.064626145 | D16: ='Data Sheet'!C63/'Data Sheet'!C$65 -> 0.090305676 | E16: ='Data Sheet'!D63/'Data Sheet'!D$65 -> 0.074612566 | F16: ='Data Sheet'!E63/'Data Sheet'!E$65 -> 0.063610241 | G16: ='Data Sheet'!F63/'Data Sheet'!F$65 -> 0.051588289 | H16: ='Data Sheet'!G63/'Data Sheet'!G$65 -> 0.050935446 | I16: ='Data Sheet'!H63/'Data Sheet'!H$65 -> 0.072079768 | J16: ='Data Sheet'!I63/'Data Sheet'!I$65 -> 0.089282796 | ... L16: ='Data Sheet'!K63/'Data Sheet'!K$65 -> 0.062164516
B17: Receivables | C17: ='Data Sheet'!B66/'Data Sheet'!B$65 -> 0.053006389 | D17: ='Data Sheet'!C66/'Data Sheet'!C$65 -> 0.051564319 | E17: ='Data Sheet'!D66/'Data Sheet'!D$65 -> 0.051638166 | F17: ='Data Sheet'!E66/'Data Sheet'!E$65 -> 0.060800116 | G17: ='Data Sheet'!F66/'Data Sheet'!F$65 -> 0.062139199 | H17: ='Data Sheet'!G66/'Data Sheet'!G$65 -> 0.034895094 | I17: ='Data Sheet'!H66/'Data Sheet'!H$65 -> 0.037120014 | J17: ='Data Sheet'!I66/'Data Sheet'!I$65 -> 0.037810927 | ... L17: ='Data Sheet'!K66/'Data Sheet'!K$65 -> 0.045875141
B18: Inventory | C18: ='Data Sheet'!B67/'Data Sheet'!B$65 -> 0.12334815 | D18: ='Data Sheet'!C67/'Data Sheet'!C$65 -> 0.12407941 | E18: ='Data Sheet'!D67/'Data Sheet'!D$65 -> 0.12871547 | F18: ='Data Sheet'!E67/'Data Sheet'!E$65 -> 0.12878571 | G18: ='Data Sheet'!F67/'Data Sheet'!F$65 -> 0.12761951 | H18: ='Data Sheet'!G67/'Data Sheet'!G$65 -> 0.11698717 | I18: ='Data Sheet'!H67/'Data Sheet'!H$65 -> 0.10565506 | J18: ='Data Sheet'!I67/'Data Sheet'!I$65 -> 0.10709348 | ... L18: ='Data Sheet'!K67/'Data Sheet'!K$65 -> 0.1293251
B19: Other Assets | C19: ='Data Sheet'!B74/'Data Sheet'!B$65 -> 0.13016959 | D19: ='Data Sheet'!C74/'Data Sheet'!C$65 -> 0.11239037 | E19: ='Data Sheet'!D74/'Data Sheet'!D$65 -> 0.13706336 | F19: ='Data Sheet'!E74/'Data Sheet'!E$65 -> 0.14757967 | G19: ='Data Sheet'!F74/'Data Sheet'!F$65 -> 0.18369349 | H19: ='Data Sheet'!G74/'Data Sheet'!G$65 -> 0.18360001 | I19: ='Data Sheet'!H74/'Data Sheet'!H$65 -> 0.1806891 | J19: ='Data Sheet'!I74/'Data Sheet'!I$65 -> 0.18909466 | ... L19: ='Data Sheet'!K74/'Data Sheet'!K$65 -> 0.21384155
B20: Cash & Bank | C20: ='Data Sheet'!B68/'Data Sheet'!B$65 -> 0.13532979 | D20: ='Data Sheet'!C68/'Data Sheet'!C$65 -> 0.11573799 | E20: ='Data Sheet'!D68/'Data Sheet'!D$65 -> 0.13235686 | F20: ='Data Sheet'!E68/'Data Sheet'!E$65 -> 0.10579088 | G20: ='Data Sheet'!F68/'Data Sheet'!F$65 -> 0.10679898 | H20: ='Data Sheet'!G68/'Data Sheet'!G$65 -> 0.10533773 | I20: ='Data Sheet'!H68/'Data Sheet'!H$65 -> 0.13699234 | J20: ='Data Sheet'!I68/'Data Sheet'!I$65 -> 0.12359146 | ... L20: ='Data Sheet'!K68/'Data Sheet'!K$65 -> 0.12396248
B21: Total Assets | C21: ='Data Sheet'!B17/'Data Sheet'!B$17 -> 1 | D21: =SUM(D14:D20) -> 1 | E21: =SUM(E14:E20) -> 1 | F21: =SUM(F14:F20) -> 1 | G21: =SUM(G14:G20) -> 1 | H21: =SUM(H14:H20) -> 1 | I21: =SUM(I14:I20) -> 1 | J21: =SUM(J14:J20) -> 1 | K21: =SUM(K14:K20) -> 1 | L21: =SUM(L14:L20) -> 1
A23: # | B23: Common Size Income Statement
B25: Particulars | C25: ='Data Sheet'!B16 -> 42094 | D25: ='Data Sheet'!C16 -> 42460 | E25: ='Data Sheet'!D16 -> 42825 | F25: ='Data Sheet'!E16 -> 43190 | G25: ='Data Sheet'!F16 -> 43555 | H25: ='Data Sheet'!G16 -> 43921 | I25: ='Data Sheet'!H16 -> 44286 | J25: ='Data Sheet'!I16 -> 44651 | ... L25: ='Data Sheet'!K16 -> 45382
B26: Sales | C26: ='Data Sheet'!B17/'Data Sheet'!B$17 -> 1 | D26: ='Data Sheet'!C17/'Data Sheet'!C$17 -> 1 | E26: ='Data Sheet'!D17/'Data Sheet'!D$17 -> 1 | F26: ='Data Sheet'!E17/'Data Sheet'!E$17 -> 1 | G26: ='Data Sheet'!F17/'Data Sheet'!F$17 -> 1 | H26: ='Data Sheet'!G17/'Data Sheet'!G$17 -> 1 | I26: ='Data Sheet'!H17/'Data Sheet'!H$17 -> 1 | J26: ='Data Sheet'!I17/'Data Sheet'!I$17 -> 1 | ... L26: ='Data Sheet'!K17/'Data Sheet'!K$17 -> 1
B27: Raw Material Cost | C27: ='Data Sheet'!B18/'Data Sheet'!B$17 -> 0.62034881 | D27: ='Data Sheet'!C18/'Data Sheet'!C$17 -> 0.60844786 | E27: ='Data Sheet'!D18/'Data Sheet'!D$17 -> 0.64256171 | F27: ='Data Sheet'!E18/'Data Sheet'!E$17 -> 0.64447357 | G27: ='Data Sheet'!F18/'Data Sheet'!F$17 -> 0.64340246 | H27: ='Data Sheet'!G18/'Data Sheet'!G$17 -> 0.63163559 | I27: ='Data Sheet'!H18/'Data Sheet'!H$17 -> 0.6149343 | J27: ='Data Sheet'!I18/'Data Sheet'!I$17 -> 0.64389657 | ... L27: ='Data Sheet'!K18/'Data Sheet'!K$17 -> 0.62640748
B28: Change in Inventory | C28: ='Data Sheet'!B19/'Data Sheet'!B$17 -> 0.012655278 | D28: ='Data Sheet'!C19/'Data Sheet'!C$17 -> 0.010075204 | E28: ='Data Sheet'!D19/'Data Sheet'!D$17 -> 0.027438359 | F28: ='Data Sheet'!E19/'Data Sheet'!E$17 -> 0.007019642 | G28: ='Data Sheet'!F19/'Data Sheet'!F$17 -> -0.0068003275 | H28: ='Data Sheet'!G19/'Data Sheet'!G$17 -> -0.008546395 | I28: ='Data Sheet'!H19/'Data Sheet'!H$17 -> -0.018752035 | J28: ='Data Sheet'!I19/'Data Sheet'!I$17 -> -0.0057118668 | ... L28: ='Data Sheet'!K19/'Data Sheet'!K$17 -> 0.0035748589
B29: Power and Fuel | C29: ='Data Sheet'!B20/'Data Sheet'!B$17 -> 0.0042626324 | D29: ='Data Sheet'!C20/'Data Sheet'!C$17 -> 0.0041884213 | E29: ='Data Sheet'!D20/'Data Sheet'!D$17 -> 0.0043005273 | F29: ='Data Sheet'!E20/'Data Sheet'!E$17 -> 0.004486633 | G29: ='Data Sheet'!F20/'Data Sheet'!F$17 -> 0.0052524952 | H29: ='Data Sheet'!G20/'Data Sheet'!G$17 -> 0.0048452899 | I29: ='Data Sheet'!H20/'Data Sheet'!H$17 -> 0.0044551377 | J29: ='Data Sheet'!I20/'Data Sheet'!I$17 -> 0.0078228109 | ... L29: ='Data Sheet'!K20/'Data Sheet'!K$17 -> 0.0050125161
B30: Other Mfr. Exp | C30: ='Data Sheet'!B21/'Data Sheet'!B$17 -> 0.061457793 | D30: ='Data Sheet'!C21/'Data Sheet'!C$17 -> 0.044320546 | E30: ='Data Sheet'!D21/'Data Sheet'!D$17 -> 0.037329068 | F30: ='Data Sheet'!E21/'Data Sheet'!E$17 -> 0.037632111 | G30: ='Data Sheet'!F21/'Data Sheet'!F$17 -> 0.038731543 | H30: ='Data Sheet'!G21/'Data Sheet'!G$17 -> 0.044208832 | I30: ='Data Sheet'!H21/'Data Sheet'!H$17 -> 0.033119871 | J30: ='Data Sheet'!I21/'Data Sheet'!I$17 -> 0.033856195 | ... L30: ='Data Sheet'!K21/'Data Sheet'!K$17 -> 0.039080257
B31: Employee Cost | C31: ='Data Sheet'!B22/'Data Sheet'!B$17 -> 0.097439008 | D31: ='Data Sheet'!C22/'Data Sheet'!C$17 -> 0.10577314 | E31: ='Data Sheet'!D22/'Data Sheet'!D$17 -> 0.10505627 | F31: ='Data Sheet'!E22/'Data Sheet'!E$17 -> 0.10392742 | G31: ='Data Sheet'!F22/'Data Sheet'!F$17 -> 0.1101015 | H31: ='Data Sheet'!G22/'Data Sheet'!G$17 -> 0.11659263 | I31: ='Data Sheet'!H22/'Data Sheet'!H$17 -> 0.11068479 | J31: ='Data Sheet'!I22/'Data Sheet'!I$17 -> 0.11064148 | ... L31: ='Data Sheet'!K22/'Data Sheet'!K$17 -> 0.09701746
B32: Selling and admin | C32: ='Data Sheet'!B23/'Data Sheet'!B$17 -> 0.089691068 | D32: ='Data Sheet'!C23/'Data Sheet'!C$17 -> 0.080542957 | E32: ='Data Sheet'!D23/'Data Sheet'!D$17 -> 0.11138381 | F32: ='Data Sheet'!E23/'Data Sheet'!E$17 -> 0.10634378 | G32: ='Data Sheet'!F23/'Data Sheet'!F$17 -> 0.10836581 | H32: ='Data Sheet'!G23/'Data Sheet'!G$17 -> 0.11203335 | I32: ='Data Sheet'!H23/'Data Sheet'!H$17 -> 0.092138806 | J32: ='Data Sheet'!I23/'Data Sheet'!I$17 -> 0.10488425 | ... L32: ='Data Sheet'!K23/'Data Sheet'!K$17 -> 0.097653844
B33: Other Expenses | C33: ='Data Sheet'!B24/'Data Sheet'!B$17 -> -0.0096502882 | D33: ='Data Sheet'!C24/'Data Sheet'!C$17 -> 0.026183832 | E33: ='Data Sheet'!D24/'Data Sheet'!D$17 -> 0.017094283 | F33: ='Data Sheet'!E24/'Data Sheet'!E$17 -> 0.0022582367 | G33: ='Data Sheet'!F24/'Data Sheet'!F$17 -> 0.0056592338 | H33: ='Data Sheet'!G24/'Data Sheet'!G$17 -> 0.013239885 | I33: ='Data Sheet'!H24/'Data Sheet'!H$17 -> -0.0033407828 | J33: ='Data Sheet'!I24/'Data Sheet'!I$17 -> 0.0044105011 | ... L33: ='Data Sheet'!K24/'Data Sheet'!K$17 -> 0.0024486001
B34: Depreciation | C34: ='Data Sheet'!B26/'Data Sheet'!B$17 -> 0.050876584 | D34: ='Data Sheet'!C26/'Data Sheet'!C$17 -> 0.061201426 | E34: ='Data Sheet'!D26/'Data Sheet'!D$17 -> 0.066390387 | F34: ='Data Sheet'!E26/'Data Sheet'!E$17 -> 0.073927472 | G34: ='Data Sheet'!F26/'Data Sheet'!F$17 -> 0.078130605 | H34: ='Data Sheet'!G26/'Data Sheet'!G$17 -> 0.082068398 | I34: ='Data Sheet'!H26/'Data Sheet'!H$17 -> 0.094264231 | J34: ='Data Sheet'!I26/'Data Sheet'!I$17 -> 0.089191478 | ... L34: ='Data Sheet'!K26/'Data Sheet'!K$17 -> 0.06227084
B35: Interest | C35: ='Data Sheet'!B27/'Data Sheet'!B$17 -> 0.018473586 | D35: ='Data Sheet'!C27/'Data Sheet'!C$17 -> 0.017905727 | E35: ='Data Sheet'!D27/'Data Sheet'!D$17 -> 0.01571423 | F35: ='Data Sheet'!E27/'Data Sheet'!E$17 -> 0.016058248 | G35: ='Data Sheet'!F27/'Data Sheet'!F$17 -> 0.019072102 | H35: ='Data Sheet'!G27/'Data Sheet'!G$17 -> 0.027744997 | I35: ='Data Sheet'!H27/'Data Sheet'!H$17 -> 0.032415293 | J35: ='Data Sheet'!I27/'Data Sheet'!I$17 -> 0.033441332 | ... L35: ='Data Sheet'!K27/'Data Sheet'!K$17 -> 0.022802299
B36: Profit before tax | C36: ='Data Sheet'!B28/'Data Sheet'!B$17 -> 0.082469388 | D36: ='Data Sheet'!C28/'Data Sheet'!C$17 -> 0.051734106 | E36: ='Data Sheet'!D28/'Data Sheet'!D$17 -> 0.034538557 | F36: ='Data Sheet'!E28/'Data Sheet'!E$17 -> 0.038261059 | G36: ='Data Sheet'!F28/'Data Sheet'!F$17 -> -0.10389917 | H36: ='Data Sheet'!G28/'Data Sheet'!G$17 -> -0.040525768 | I36: ='Data Sheet'!H28/'Data Sheet'!H$17 -> -0.041931546 | J36: ='Data Sheet'!I28/'Data Sheet'!I$17 -> -0.025151083 | ... L36: ='Data Sheet'!K28/'Data Sheet'!K$17 -> 0.063834979
B37: Tax | C37: ='Data Sheet'!B29/'Data Sheet'!B$17 -> 0.029042938 | D37: ='Data Sheet'!C29/'Data Sheet'!C$17 -> 0.011078919 | E37: ='Data Sheet'!D29/'Data Sheet'!D$17 -> 0.012055322 | F37: ='Data Sheet'!E29/'Data Sheet'!E$17 -> 0.01489255 | G37: ='Data Sheet'!F29/'Data Sheet'!F$17 -> -0.0080726731 | H37: ='Data Sheet'!G29/'Data Sheet'!G$17 -> 0.0015139735 | I37: ='Data Sheet'!H29/'Data Sheet'!H$17 -> 0.010175794 | J37: ='Data Sheet'!I29/'Data Sheet'!I$17 -> 0.015195672 | ... L37: ='Data Sheet'!K29/'Data Sheet'!K$17 -> -0.008795149
B38: Net profit | C38: ='Data Sheet'!B30/'Data Sheet'!B$17 -> 0.053147683 | D38: ='Data Sheet'!C30/'Data Sheet'!C$17 -> 0.042407971 | E38: ='Data Sheet'!D30/'Data Sheet'!D$17 -> 0.027640219 | F38: ='Data Sheet'!E30/'Data Sheet'!E$17 -> 0.030831402 | G38: ='Data Sheet'!F30/'Data Sheet'!F$17 -> -0.095470566 | H38: ='Data Sheet'!G30/'Data Sheet'!G$17 -> -0.046236426 | I38: ='Data Sheet'!H30/'Data Sheet'!H$17 -> -0.053849771 | J38: ='Data Sheet'!I30/'Data Sheet'!I$17 -> -0.04108932 | ... L38: ='Data Sheet'!K30/'Data Sheet'!K$17 -> 0.071699244
B39: EBITDA | C39: ='Data Sheet'!B34/'Data Sheet'!B$17 -> 0.15154079 | D39: ='Data Sheet'!C34/'Data Sheet'!C$17 -> 0.13259404 | E39: ='Data Sheet'!D34/'Data Sheet'!D$17 -> 0.12180016 | F39: ='Data Sheet'!E34/'Data Sheet'!E$17 -> 0.13570967 | G39: ='Data Sheet'!F34/'Data Sheet'!F$17 -> -0.0063405317 | H39: ='Data Sheet'!G34/'Data Sheet'!G$17 -> 0.065090942 | I39: ='Data Sheet'!H34/'Data Sheet'!H$17 -> 0.083005548 | J39: ='Data Sheet'!I34/'Data Sheet'!I$17 -> 0.096739163 | ... L39: ='Data Sheet'!K34/'Data Sheet'!K$17 -> 0.14797723

Sheet Ratio Analysis
B2: ="Ratio Analysis - "&'Data Sheet'!B1 -> Ratio Analysis - TATA MOTORS LTD
B3: Year | C3: ='Data Sheet'!B16 -> 42094 | D3: ='Data Sheet'!C16 -> 42460 | E3: ='Data Sheet'!D16 -> 42825 | F3: ='Data Sheet'!E16 -> 43190 | G3: ='Data Sheet'!F16 -> 43555 | H3: ='Data Sheet'!G16 -> 43921 | I3: ='Data Sheet'!H16 -> 44286 | J3: ='Data Sheet'!I16 -> 44651 | ... L3: ='Data Sheet'!K16 -> 45382 | M3: Trend | N3: Mean | O3: Median
B6: SalesGrowth | D6: =IFERROR('Historical FS'!D7,0) -> 0.037569001 | E6: =IFERROR('Historical FS'!E7,0) -> -0.01228033 | F6: =IFERROR('Historical FS'!F7,0) -> 0.081047746 | G6: =IFERROR('Historical FS'!G7,0) -> 0.035629919 | H6: =IFERROR('Historical FS'!H7,0) -> -0.13536016 | I6: =IFERROR('Historical FS'!I7,0) -> -0.043181168 | J6: =IFERROR('Historical FS'!J7,0) -> 0.11472967 | K6: =IFERROR('Historical FS'!K7,0) -> 0.24245815 | L6: =IFERROR('Historical FS'!L7,0) -> 0.26580803 | N6: =IFERROR(AVERAGE(D6:L6),0) -> 0.065157874 | O6: =IFERROR(MEDIAN(C6:L6),0) -> 0.037569001
B7: EBITDA Growth | D7: =IFERROR('Historical FS'!D18/'Historical FS'!C18-1,0) -> -0.021494114 | E7: =IFERROR('Historical FS'!E18/'Historical FS'!D18-1,0) -> -0.22936587 | F7: =IFERROR('Historical FS'!F18/'Historical FS'!E18-1,0) -> 0.063165689 | G7: =IFERROR('Historical FS'!G18/'Historical FS'!F18-1,0) -> -0.21595203 | H7: =IFERROR('Historical FS'!H18/'Historical FS'!G18-1,0) -> -0.27072538 | I7: =IFERROR('Historical FS'!I18/'Historical FS'!H18-1,0) -> 0.79503554 | J7: =IFERROR('Historical FS'!J18/'Historical FS'!I18-1,0) -> -0.23437418 | K7: =IFERROR('Historical FS'!K18/'Historical FS'!J18-1,0) -> 0.28704224 | L7: =IFERROR('Historical FS'!L18/'Historical FS'!K18-1,0) -> 0.87134505 | N7: =IFERROR(AVERAGE(D7:L7),0) -> 0.11607522 | O7: =IFERROR(MEDIAN(C7:L7),0) -> -0.021494114
B8: EBIT Growth | D8: =IFERROR(('Historical FS'!D18-'Historical FS'!D24)/('Historical FS'!C18-'Historical FS'!C24)-1,0) -> -0.16114301 | E8: =IFERROR(('Historical FS'!E18-'Historical FS'!E24)/('Historical FS'!D18-'Historical FS'!D24)-1,0) -> -0.46119504 | F8: =IFERROR(('Historical FS'!F18-'Historical FS'!F24)/('Historical FS'!E18-'Historical FS'!E24)-1,0) -> -0.15231562 | G8: =IFERROR(('Historical FS'!G18-'Historical FS'!G24)/('Historical FS'!F18-'Historical FS'!F24)-1,0) -> -0.89159024 | H8: =IFERROR(('Historical FS'!H18-'Historical FS'!H24)/('Historical FS'!G18-'Historical FS'!G24)-1,0) -> -4.202347 | I8: =IFERROR(('Historical FS'!I18-'Historical FS'!I24)/('Historical FS'!H18-'Historical FS'!H24)-1,0) -> -3.5421189 | J8: =IFERROR(('Historical FS'!J18-'Historical FS'!J24)/('Historical FS'!I18-'Historical FS'!I24)-1,0) -> -1.0132255 | K8: =IFERROR(('Historical FS'!K18-'Historical FS'!K24)/('Historical FS'!J18-'Historical FS'!J24)-1,0) -> -61.168166 | L8: =IFERROR(('Historical FS'!L18-'Historical FS'!L24)/('Historical FS'!K18-'Historical FS'!K24)-1,0) -> 3.6392766 | N8: =IFERROR(AVERAGE(D8:L8),0) -> -7.5503139 | O8: =IFERROR(MEDIAN(C8:L8),0) -> -0.89159024
B9: EBT Growth | D9: =IFERROR('Historical FS'!D27/'Historical FS'!C27-1,0) -> -0.19978245 | E9: =IFERROR('Historical FS'!E27/'Historical FS'!D27-1,0) -> -0.55668252 | F9: =IFERROR('Historical FS'!F27/'Historical FS'!E27-1,0) -> -0.29861437 | G9: =IFERROR('Historical FS'!G27/'Historical FS'!F27-1,0) -> -1.8970951 | H9: =IFERROR('Historical FS'!H27/'Historical FS'!G27-1,0) -> 1.2800252 | I9: =IFERROR('Historical FS'!I27/'Historical FS'!H27-1,0) -> -1.060248 | J9: =IFERROR('Historical FS'!J27/'Historical FS'!I27-1,0) -> -15.649149 | K9: =IFERROR('Historical FS'!K27/'Historical FS'!J27-1,0) -> -0.65313669 | L9: =IFERROR('Historical FS'!L27/'Historical FS'!K27-1,0) -> -7.8141215 | N9: =IFERROR(AVERAGE(D9:L9),0) -> -2.9832005 | O9: =IFERROR(MEDIAN(C9:L9),0) -> -0.65313669
B10: Net Profit Growth | D10: =IFERROR('Historical FS'!D33/'Historical FS'!C33-1,0) -> 0.031824674 | E10: =IFERROR('Historical FS'!E33/'Historical FS'!D33-1,0) -> -0.69539895 | F10: =IFERROR('Historical FS'!F33/'Historical FS'!E33-1,0) -> -0.79011124 | G10: =IFERROR('Historical FS'!G33/'Historical FS'!F33-1,0) -> -3.5528471 | H10: =IFERROR('Historical FS'!H33/'Historical FS'!G33-1,0) -> 3.9286703 | I10: =IFERROR('Historical FS'!I33/'Historical FS'!H33-1,0) -> -0.82862505 | J10: =IFERROR('Historical FS'!J33/'Historical FS'!I33-1,0) -> 6.1952157 | K10: =IFERROR('Historical FS'!K33/'Historical FS'!J33-1,0) -> -0.70904365 | L10: =IFERROR('Historical FS'!L33/'Historical FS'!K33-1,0) -> -7.5761028 | N10: =IFERROR(AVERAGE(D10:L10),0) -> -0.44404645 | O10: =IFERROR(MEDIAN(C10:L10),0) -> -0.70904365
B11: Dividend Growth | D11: =IFERROR('Historical FS'!D42/'Historical FS'!C42-1,0) -> 0 | E11: =IFERROR('Historical FS'!E42/'Historical FS'!D42-1,0) -> -1 | F11: =IFERROR('Historical FS'!F42/'Historical FS'!E42-1,0) -> 0 | G11: =IFERROR('Historical FS'!G42/'Historical FS'!F42-1,0) -> 0 | H11: =IFERROR('Historical FS'!H42/'Historical FS'!G42-1,0) -> 0 | I11: =IFERROR('Historical FS'!I42/'Historical FS'!H42-1,0) -> 0 | J11: =IFERROR('Historical FS'!J42/'Historical FS'!I42-1,0) -> 0 | K11: =IFERROR('Historical FS'!K42/'Historical FS'!J42-1,0) -> 0 | L11: =IFERROR('Historical FS'!L42/'Historical FS'!K42-1,0) -> 1.9997122 | N11: =IFERROR(AVERAGE(D11:L11),0) -> 0.11107914 | O11: =IFERROR(MEDIAN(C11:L11),0) -> 0
B13: Gross Margin | C13: =IFERROR('Historical FS'!C13,0) -> 0.22914703 | D13: =IFERROR('Historical FS'!D13,0) -> 0.24734524 | E13: =IFERROR('Historical FS'!E13,0) -> 0.23819078 | F13: =IFERROR('Historical FS'!F13,0) -> 0.2164999 | G13: =IFERROR('Historical FS'!G13,0) -> 0.19571167 | H13: =IFERROR('Historical FS'!H13,0) -> 0.19417127 | I13: =IFERROR('Historical FS'!I13,0) -> 0.21805386 | J13: =IFERROR('Historical FS'!J13,0) -> 0.19807108 | ... L13: =IFERROR('Historical FS'!L13,0) -> 0.23605715 | N13: =IFERROR(AVERAGE(C13:L13),0) -> 0.21800982 | O13: =IFERROR(MEDIAN(C13:L13),0) -> 0.21727688
B14: EBITDA Margin | C14: =IFERROR('Historical FS'!C19,0) -> 0.14910626 | D14: =IFERROR('Historical FS'!D19,0) -> 0.14061845 | E14: =IFERROR('Historical FS'!E19,0) -> 0.10971269 | F14: =IFERROR('Historical FS'!F19,0) -> 0.10789788 | G14: =IFERROR('Historical FS'!G19,0) -> 0.081686629 | H14: =IFERROR('Historical FS'!H19,0) -> 0.068898034 | I14: =IFERROR('Historical FS'!I19,0) -> 0.12925584 | J14: =IFERROR('Historical FS'!J19,0) -> 0.088776328 | ... L14: =IFERROR('Historical FS'!L19,0) -> 0.1359547 | N14: =IFERROR(AVERAGE(C14:L14),0) -> 0.11038688 | O14: =IFERROR(MEDIAN(C14:L14),0) -> 0.10880529
B15: EBIT Margin | C15: =IFERROR(('Historical FS'!C18-'Historical FS'!C24)/'Historical FS'!C6,0) -> 0.098229671 | D15: =IFERROR(('Historical FS'!D18-'Historical FS'!D24)/'Historical FS'!D6,0) -> 0.079417028 | E15: =IFERROR(('Historical FS'!E18-'Historical FS'!E24)/'Historical FS'!E6,0) -> 0.043322301 | F15: =IFERROR(('Historical FS'!F18-'Historical FS'!F24)/'Historical FS'!F6,0) -> 0.033970412 | G15: =IFERROR(('Historical FS'!G18-'Historical FS'!G24)/'Historical FS'!G6,0) -> 0.0035560233 | H15: =IFERROR(('Historical FS'!H18-'Historical FS'!H24)/'Historical FS'!H6,0) -> -0.013170363 | I15: =IFERROR(('Historical FS'!I18-'Historical FS'!I24)/'Historical FS'!I6,0) -> 0.034991608 | J15: =IFERROR(('Historical FS'!J18-'Historical FS'!J24)/'Historical FS'!J6,0) -> -0.00041514993 | ... L15: =IFERROR(('Historical FS'!L18-'Historical FS'!L24)/'Historical FS'!L6,0) -> 0.073683863 | N15: =IFERROR(AVERAGE(C15:L15),0) -> 0.037368974 | O15: =IFERROR(MEDIAN(C15:L15),0) -> 0.03448101
B16: EBT Margin | C16: =IFERROR('Historical FS'!C28,0) -> 0.079756085 | D16: =IFERROR('Historical FS'!D28,0) -> 0.061511301 | E16: =IFERROR('Historical FS'!E28,0) -> 0.027608071 | F16: =IFERROR('Historical FS'!F28,0) -> 0.017912164 | G16: =IFERROR('Historical FS'!G28,0) -> -0.015516079 | H16: =IFERROR('Historical FS'!H28,0) -> -0.04091536 | I16: =IFERROR('Historical FS'!I28,0) -> 0.0025763152 | J16: =IFERROR('Historical FS'!J28,0) -> -0.033856482 | ... L16: =IFERROR('Historical FS'!L28,0) -> 0.050881564 | N16: =IFERROR(AVERAGE(C16:L16),0) -> 0.014050569 | O16: =IFERROR(MEDIAN(C16:L16),0) -> 0.01024424
B17: Net Profit Margin | C17: =IFERROR('Historical FS'!C34,0) -> 0.050713147 | D17: =IFERROR('Historical FS'!D34,0) -> 0.050432382 | E17: =IFERROR('Historical FS'!E34,0) -> 0.015552749 | F17: =IFERROR('Historical FS'!F34,0) -> 0.0030196143 | G17: =IFERROR('Historical FS'!G34,0) -> -0.0074434057 | H17: =IFERROR('Historical FS'!H34,0) -> -0.042429334 | I17: =IFERROR('Historical FS'!I34,0) -> -0.0075994792 | J17: =IFERROR('Historical FS'!J34,0) -> -0.049052155 | ... L17: =IFERROR('Historical FS'!L34,0) -> 0.059676713 | N17: =IFERROR(AVERAGE(C17:L17),0) -> 0.0061383298 | O17: =IFERROR(MEDIAN(C17:L17),0) -> -0.0022118957
B19: SalesExpenses%Sales | C19: =IFERROR('Historical FS'!C16,0) -> 0.08004078 | D19: =IFERROR('Historical FS'!D16,0) -> 0.10672679 | E19: =IFERROR('Historical FS'!E16,0) -> 0.1284781 | F19: =IFERROR('Historical FS'!F16,0) -> 0.10860202 | G19: =IFERROR('Historical FS'!G16,0) -> 0.11402505 | H19: =IFERROR('Historical FS'!H16,0) -> 0.12527324 | I19: =IFERROR('Historical FS'!I16,0) -> 0.088798023 | J19: =IFERROR('Historical FS'!J16,0) -> 0.10929475 | ... L19: =IFERROR('Historical FS'!L16,0) -> 0.10010244 | N19: =IFERROR(AVERAGE(C19:L19),0) -> 0.10762294 | O19: =IFERROR(MEDIAN(C19:L19),0) -> 0.10894839
B20: Depreciation%Sales | C20: =IFERROR('Historical FS'!C25,0) -> 0.050876584 | D20: =IFERROR('Historical FS'!D25,0) -> 0.061201426 | E20: =IFERROR('Historical FS'!E25,0) -> 0.066390387 | F20: =IFERROR('Historical FS'!F25,0) -> 0.073927472 | G20: =IFERROR('Historical FS'!G25,0) -> 0.078130605 | H20: =IFERROR('Historical FS'!H25,0) -> 0.082068398 | I20: =IFERROR('Historical FS'!I25,0) -> 0.094264231 | J20: =IFERROR('Historical FS'!J25,0) -> 0.089191478 | ... L20: =IFERROR('Historical FS'!L25,0) -> 0.06227084 | N20: =IFERROR(AVERAGE(C20:L20),0) -> 0.073017903 | O20: =IFERROR(MEDIAN(C20:L20),0) -> 0.072892542
B21: OperatingIncome%Sales | C21: =C15 -> 0.098229671 | D21: =D15 -> 0.079417028 | E21: =E15 -> 0.043322301 | F21: =F15 -> 0.033970412 | G21: =G15 -> 0.0035560233 | H21: =H15 -> -0.013170363 | I21: =I15 -> 0.034991608 | J21: =J15 -> -0.00041514993 | ... L21: =L15 -> 0.073683863 | N21: =IFERROR(AVERAGE(C21:L21),0) -> 0.037368974 | O21: =IFERROR(MEDIAN(C21:L21),0) -> 0.03448101
B23: Return on Capital Employed | C23: =IFERROR(('Historical FS'!C18-'Historical FS'!C24)/(SUM('Historical FS'!C50:C52)),0) -> 0.19904181 | D23: =IFERROR(('Historical FS'!D18-'Historical FS'!D24)/(SUM('Historical FS'!D50:D52)),0) -> 0.1462081 | E23: =IFERROR(('Historical FS'!E18-'Historical FS'!E24)/(SUM('Historical FS'!E50:E52)),0) -> 0.085490986 | F23: =IFERROR(('Historical FS'!F18-'Historical FS'!F24)/(SUM('Historical FS'!F50:F52)),0) -> 0.053716114 | G23: =IFERROR(('Historical FS'!G18-'Historical FS'!G24)/(SUM('Historical FS'!G50:G52)),0) -> 0.0064542734 | H23: =IFERROR(('Historical FS'!H18-'Historical FS'!H24)/(SUM('Historical FS'!H50:H52)),0) -> -0.018302178 | I23: =IFERROR(('Historical FS'!I18-'Historical FS'!I24)/(SUM('Historical FS'!I50:I52)),0) -> 0.044284325 | J23: =IFERROR(('Historical FS'!J18-'Historical FS'!J24)/(SUM('Historical FS'!J50:J52)),0) -> -0.00060520306 | ... L23: =IFERROR(('Historical FS'!L18-'Historical FS'!L24)/(SUM('Historical FS'!L50:L52)),0) -> 0.16790573 | N23: =IFERROR(AVERAGE(C23:L23),0) -> 0.072295691 | O23: =IFERROR(MEDIAN(C23:L23),0) -> 0.049000219
B24: Retained Earnings% | C24: =IFERROR('Historical FS'!C45,0) -> 1 | D24: =IFERROR('Historical FS'!D45,0) -> 0.99506766 | E24: =IFERROR('Historical FS'!E45,0) -> 1 | F24: =IFERROR('Historical FS'!F45,0) -> 1 | G24: =IFERROR('Historical FS'!G45,0) -> 0 | H24: =IFERROR('Historical FS'!H45,0) -> 0 | I24: =IFERROR('Historical FS'!I45,0) -> 0 | J24: =IFERROR('Historical FS'!J45,0) -> 0 | ... L24: =IFERROR('Historical FS'!L45,0) -> 0.91201148 | N24: =IFERROR(AVERAGE(C24:L24),0) -> 0.49070791 | O24: =IFERROR(MEDIAN(C24:L24),0) -> 0.45600574
B25: Return on Equity% | C25: =IFERROR('Historical FS'!C33/(SUM('Historical FS'!C50:C51)),0) -> 0.2372052 | D25: =IFERROR('Historical FS'!D33/(SUM('Historical FS'!D50:D51)),0) -> 0.17441317 | E25: =IFERROR('Historical FS'!E33/(SUM('Historical FS'!E50:E51)),0) -> 0.07224119 | F25: =IFERROR('Historical FS'!F33/(SUM('Historical FS'!F50:F51)),0) -> 0.0092254981 | G25: =IFERROR('Historical FS'!G33/(SUM('Historical FS'!G50:G51)),0) -> -0.037345737 | H25: =IFERROR('Historical FS'!H33/(SUM('Historical FS'!H50:H51)),0) -> -0.17560555 | I25: =IFERROR('Historical FS'!I33/(SUM('Historical FS'!I50:I51)),0) -> -0.034360592 | J25: =IFERROR('Historical FS'!J33/(SUM('Historical FS'!J50:J51)),0) -> -0.30651638 | ... L25: =IFERROR('Historical FS'!L33/(SUM('Historical FS'!L50:L51)),0) -> 0.3077567 | N25: =IFERROR(AVERAGE(C25:L25),0) -> 0.01593272 | O25: =IFERROR(MEDIAN(C25:L25),0) -> -0.012567547
B26: Self Sustained Growth Rate | C26: =IFERROR(C24*C25,0) -> 0.2372052 | D26: =IFERROR(D24*D25,0) -> 0.1735529 | E26: =IFERROR(E24*E25,0) -> 0.07224119 | F26: =IFERROR(F24*F25,0) -> 0.0092254981 | G26: =IFERROR(G24*G25,0) -> 0 | H26: =IFERROR(H24*H25,0) -> 0 | I26: =IFERROR(I24*I25,0) -> 0 | J26: =IFERROR(J24*J25,0) -> 0 | ... L26: =IFERROR(L24*L25,0) -> 0.28067765 | N26: =IFERROR(AVERAGE(C26:L26),0) -> 0.077290244 | O26: =IFERROR(MEDIAN(C26:L26),0) -> 0.004612749
B27: Interest Coverage Ratio | C27: =IFERROR(('Historical FS'!C18-'Historical FS'!C24)/'Historical FS'!C21,0) -> 5.317304 | D27: =IFERROR(('Historical FS'!D18-'Historical FS'!D24)/'Historical FS'!D21,0) -> 4.4352864 | E27: =IFERROR(('Historical FS'!E18-'Historical FS'!E24)/'Historical FS'!E21,0) -> 2.7568835 | F27: =IFERROR(('Historical FS'!F18-'Historical FS'!F24)/'Historical FS'!F21,0) -> 2.1154494 | G27: =IFERROR(('Historical FS'!G18-'Historical FS'!G24)/'Historical FS'!G21,0) -> 0.18645157 | H27: =IFERROR(('Historical FS'!H18-'Historical FS'!H24)/'Historical FS'!H21,0) -> -0.47469327 | I27: =IFERROR(('Historical FS'!I18-'Historical FS'!I24)/'Historical FS'!I21,0) -> 1.0794784 | J27: =IFERROR(('Historical FS'!J18-'Historical FS'!J24)/'Historical FS'!J21,0) -> -0.012414276 | ... L27: =IFERROR(('Historical FS'!L18-'Historical FS'!L24)/'Historical FS'!L21,0) -> 3.2314225 | N27: =IFERROR(AVERAGE(C27:L27),0) -> 1.9315375 | O27: =IFERROR(MEDIAN(C27:L27),0) -> 1.5974639
B29: Debtor Turnover Ratio | C29: =IFERROR('Historical FS'!C6/'Historical FS'!C62,0) -> 20.920168 | D29: =IFERROR('Historical FS'!D6/'Historical FS'!D62,0) -> 20.119918 | E29: =IFERROR('Historical FS'!E6/'Historical FS'!E62,0) -> 19.160353 | F29: =IFERROR('Historical FS'!F6/'Historical FS'!F62,0) -> 14.655712 | G29: =IFERROR('Historical FS'!G6/'Historical FS'!G62,0) -> 15.894699 | H29: =IFERROR('Historical FS'!H6/'Historical FS'!H62,0) -> 23.366617 | I29: =IFERROR('Historical FS'!I6/'Historical FS'!I62,0) -> 19.701331 | J29: =IFERROR('Historical FS'!J6/'Historical FS'!J62,0) -> 22.379918 | ... L29: =IFERROR('Historical FS'!L6/'Historical FS'!L62,0) -> 25.833688 | N29: =IFERROR(AVERAGE(C29:L29),0) -> 20.401535 | O29: =IFERROR(MEDIAN(C29:L29),0) -> 20.520043
B30: Creditor Turnover Ratio | C30: =IFERROR('Historical FS'!C6/'Historical FS'!C53,0) -> 2.4493011 | D30: =IFERROR('Historical FS'!D6/'Historical FS'!D53,0) -> 2.3769604 | E30: =IFERROR('Historical FS'!E6/'Historical FS'!E53,0) -> 1.9842808 | F30: =IFERROR('Historical FS'!F6/'Historical FS'!F53,0) -> 2.041478 | G30: =IFERROR('Historical FS'!G6/'Historical FS'!G53,0) -> 2.1667848 | H30: =IFERROR('Historical FS'!H6/'Historical FS'!H53,0) -> 1.9731057 | I30: =IFERROR('Historical FS'!I6/'Historical FS'!I53,0) -> 1.7323685 | J30: =IFERROR('Historical FS'!J6/'Historical FS'!J53,0) -> 2.0170312 | ... L30: =IFERROR('Historical FS'!L6/'Historical FS'!L53,0) -> 2.4694234 | N30: =IFERROR(AVERAGE(C30:L30),0) -> 2.143934 | O30: =IFERROR(MEDIAN(C30:L30),0) -> 2.1041314
B31: Inventory Turnover | C31: =IFERROR('Historical FS'!C9/'Historical FS'!C63,0) -> 6.9299851 | D31: =IFERROR('Historical FS'!D9/'Historical FS'!D63,0) -> 6.2932009 | E31: =IFERROR('Historical FS'!E9/'Historical FS'!E63,0) -> 5.8558479 | F31: =IFERROR('Historical FS'!F9/'Historical FS'!F63,0) -> 5.4210412 | G31: =IFERROR('Historical FS'!G9/'Historical FS'!G63,0) -> 6.2246171 | H31: =IFERROR('Historical FS'!H9/'Historical FS'!H63,0) -> 5.6164867 | I31: =IFERROR('Historical FS'!I9/'Historical FS'!I63,0) -> 5.4124043 | J31: =IFERROR('Historical FS'!J9/'Historical FS'!J63,0) -> 6.3364885 | ... L31: =IFERROR('Historical FS'!L9/'Historical FS'!L63,0) -> 7.0007064 | N31: =IFERROR(AVERAGE(C31:L31),0) -> 6.1823719 | O31: =IFERROR(MEDIAN(C31:L31),0) -> 6.258909
B32: Fixed Asset Turnover | C32: =IFERROR('Historical FS'!C6/'Historical FS'!C56,0) -> 2.9742371 | D32: =IFERROR('Historical FS'!D6/'Historical FS'!D56,0) -> 2.5463128 | E32: =IFERROR('Historical FS'!E6/'Historical FS'!E56,0) -> 2.8109343 | F32: =IFERROR('Historical FS'!F6/'Historical FS'!F56,0) -> 2.4012949 | G32: =IFERROR('Historical FS'!G6/'Historical FS'!G56,0) -> 2.714432 | H32: =IFERROR('Historical FS'!H6/'Historical FS'!H56,0) -> 2.0539206 | I32: =IFERROR('Historical FS'!I6/'Historical FS'!I56,0) -> 1.8008727 | J32: =IFERROR('Historical FS'!J6/'Historical FS'!J56,0) -> 2.0053489 | ... L32: =IFERROR('Historical FS'!L6/'Historical FS'!L56,0) -> 3.6107195 | N32: =IFERROR(AVERAGE(C32:L32),0) -> 2.5537452 | O32: =IFERROR(MEDIAN(C32:L32),0) -> 2.582846
B33: Capital Turnover Ratio | C33: =IFERROR('Historical FS'!C6/(SUM('Historical FS'!C50:C51)),0) -> 4.6773907 | D33: =IFERROR('Historical FS'!D6/(SUM('Historical FS'!D50:D51)),0) -> 3.4583567 | E33: =IFERROR('Historical FS'!E6/(SUM('Historical FS'!E50:E51)),0) -> 4.6449144 | F33: =IFERROR('Historical FS'!F6/(SUM('Historical FS'!F50:F51)),0) -> 3.0551909 | G33: =IFERROR('Historical FS'!G6/(SUM('Historical FS'!G50:G51)),0) -> 5.0172916 | H33: =IFERROR('Historical FS'!H6/(SUM('Historical FS'!H50:H51)),0) -> 4.138777 | I33: =IFERROR('Historical FS'!I6/(SUM('Historical FS'!I50:I51)),0) -> 4.5214404 | J33: =IFERROR('Historical FS'!J6/(SUM('Historical FS'!J50:J51)),0) -> 6.2487853 | ... L33: =IFERROR('Historical FS'!L6/(SUM('Historical FS'!L50:L51)),0) -> 5.1570652 | N33: =IFERROR(AVERAGE(C33:L33),0) -> 4.855278 | O33: =IFERROR(MEDIAN(C33:L33),0) -> 4.6611525
B35: ( In Days )
B36: Debtor Days | C36: =IFERROR(365/C29,0) -> 17.447278 | D36: =IFERROR(365/D29,0) -> 18.141227 | E36: =IFERROR(365/E29,0) -> 19.049753 | F36: =IFERROR(365/F29,0) -> 24.904965 | G36: =IFERROR(365/G29,0) -> 22.963631 | H36: =IFERROR(365/H29,0) -> 15.620575 | I36: =IFERROR(365/I29,0) -> 18.526667 | J36: =IFERROR(365/J29,0) -> 16.309265 | ... L36: =IFERROR(365/L29,0) -> 14.128838 | N36: =IFERROR(AVERAGE(C36:L36),0) -> 18.369598 | O36: =IFERROR(MEDIAN(C36:L36),0) -> 17.794253
B37: Payable Days | C37: =IFERROR(365/C30,0) -> 149.02211 | D37: =IFERROR(365/D30,0) -> 153.55746 | E37: =IFERROR(365/E30,0) -> 183.94574 | F37: =IFERROR(365/F30,0) -> 178.79203 | G37: =IFERROR(365/G30,0) -> 168.45236 | H37: =IFERROR(365/H30,0) -> 184.98755 | I37: =IFERROR(365/I30,0) -> 210.69421 | J37: =IFERROR(365/J30,0) -> 180.95902 | ... L37: =IFERROR(365/L30,0) -> 147.80778 | N37: =IFERROR(AVERAGE(C37:L37),0) -> 172.19978 | O37: =IFERROR(MEDIAN(C37:L37),0) -> 173.62219
B38: Inventory Days | C38: =IFERROR(365/C31,0) -> 52.669666 | D38: =IFERROR(365/D31,0) -> 57.999102 | E38: =IFERROR(365/E31,0) -> 62.330854 | F38: =IFERROR(365/F31,0) -> 67.330239 | G38: =IFERROR(365/G31,0) -> 58.638145 | H38: =IFERROR(365/H31,0) -> 64.987245 | I38: =IFERROR(365/I31,0) -> 67.437682 | J38: =IFERROR(365/J31,0) -> 57.602882 | ... L38: =IFERROR(365/L31,0) -> 52.137595 | N38: =IFERROR(AVERAGE(C38:L38),0) -> 59.534449 | O38: =IFERROR(MEDIAN(C38:L38),0) -> 58.318623
B39: Cash Conversion Cycle | C39: =IFERROR(SUM(C36,C38)-C37,0) -> -78.905161 | D39: =IFERROR(SUM(D36,D38)-D37,0) -> -77.417131 | E39: =IFERROR(SUM(E36,E38)-E37,0) -> -102.56514 | F39: =IFERROR(SUM(F36,F38)-F37,0) -> -86.556826 | G39: =IFERROR(SUM(G36,G38)-G37,0) -> -86.850581 | H39: =IFERROR(SUM(H36,H38)-H37,0) -> -104.37973 | I39: =IFERROR(SUM(I36,I38)-I37,0) -> -124.72986 | J39: =IFERROR(SUM(J36,J38)-J37,0) -> -107.04688 | ... L39: =IFERROR(SUM(L36,L38)-L37,0) -> -81.541349 | N39: =IFERROR(AVERAGE(C39:L39),0) -> -94.295732 | O39: =IFERROR(MEDIAN(C39:L39),0) -> -89.907627
B41: CFO/Sales | C41: =IFERROR('Historical FS'!C81/'Historical FS'!C6,0) -> 0.1210675 | D41: =IFERROR('Historical FS'!D81/'Historical FS'!D6,0) -> 0.14360971 | E41: =IFERROR('Historical FS'!E81/'Historical FS'!E6,0) -> 0.12404497 | F41: =IFERROR('Historical FS'!F81/'Historical FS'!F6,0) -> 0.059759806 | G41: =IFERROR('Historical FS'!G81/'Historical FS'!G6,0) -> 0.03865358 | H41: =IFERROR('Historical FS'!H81/'Historical FS'!H6,0) -> 0.12141666 | I41: =IFERROR('Historical FS'!I81/'Historical FS'!I6,0) -> 0.11572301 | J41: =IFERROR('Historical FS'!J81/'Historical FS'!J6,0) -> 0.012684339 | ... L41: =IFERROR('Historical FS'!L81/'Historical FS'!L6,0) -> 0.17181144 | N41: =IFERROR(AVERAGE(C41:L41),0) -> 0.10020198 | O41: =IFERROR(MEDIAN(C41:L41),0) -> 0.11839525
B42: CFO/Total Assets | C42: =IFERROR('Historical FS'!C81/'Historical FS'!C67,0) -> 0.13425206 | D42: =IFERROR('Historical FS'!D81/'Historical FS'!D67,0) -> 0.14899075 | E42: =IFERROR('Historical FS'!E81/'Historical FS'!E67,0) -> 0.12273078 | F42: =IFERROR('Historical FS'!F81/'Historical FS'!F67,0) -> 0.05325011 | G42: =IFERROR('Historical FS'!G81/'Historical FS'!G67,0) -> 0.038177516 | H42: =IFERROR('Historical FS'!H81/'Historical FS'!H67,0) -> 0.099000751 | I42: =IFERROR('Historical FS'!I81/'Historical FS'!I67,0) -> 0.08462982 | J42: =IFERROR('Historical FS'!J81/'Historical FS'!J67,0) -> 0.010733556 | ... L42: =IFERROR('Historical FS'!L81/'Historical FS'!L67,0) -> 0.20361787 | N42: =IFERROR(AVERAGE(C42:L42),0) -> 0.099177839 | O42: =IFERROR(MEDIAN(C42:L42),0) -> 0.097697963
B43: CFO/Total Debt | C43: =IFERROR('Historical FS'!C81/'Historical FS'!C52,0) -> 0.43281933 | D43: =IFERROR('Historical FS'!D81/'Historical FS'!D52,0) -> 0.56534058 | E43: =IFERROR('Historical FS'!E81/'Historical FS'!E52,0) -> 0.42560186 | F43: =IFERROR('Historical FS'!F81/'Historical FS'!F52,0) -> 0.19587305 | G43: =IFERROR('Historical FS'!G81/'Historical FS'!G52,0) -> 0.10992195 | H43: =IFERROR('Historical FS'!H81/'Historical FS'!H52,0) -> 0.25401554 | I43: =IFERROR('Historical FS'!I81/'Historical FS'!I52,0) -> 0.20338341 | J43: =IFERROR('Historical FS'!J81/'Historical FS'!J52,0) -> 0.024117606 | ... L43: =IFERROR('Historical FS'!L81/'Historical FS'!L52,0) -> 0.70146603 | N43: =IFERROR(AVERAGE(C43:L43),0) -> 0.31530894 | O43: =IFERROR(MEDIAN(C43:L43),0) -> 0.24728282

Sheet Raw FS
B2: Particulars | C2: 41334 | D2: 41699 | E2: 42064 | F2: 42430 | G2: 42795 | H2: 43160 | I2: 43525 | J2: 43891 | K2: 44256 | L2: 44621 | M2: 44986 | N2: 45352
B4: Equity Capital | C4: 96 | D4: 96 | E4: 96 | F4: 96 | G4: 96 | H4: 96 | I4: 96 | J4: 96 | K4: 96 | L4: 96 | M4: 96 | N4: 96
B5: Reserves | C5: 3288 | D5: 3943 | E5: 4646 | F5: 6429 | G5: 7508 | H5: 8314 | I5: 9375 | J5: 10034 | K5: 12710 | L5: 13716 | M5: 15896 | N5: 18632
B6: Borrowings
B7: Long term Borrowings | C7: 47 | D7: 41 | E7: 78 | F7: 73 | G7: 41 | H7: 28 | I7: 19 | J7: 19 | K7: 15 | L7: 45 | M7: 76 | N7: 54
B8: Short term Borrowings | C8: 190 | D8: 199 | E8: 332 | F8: 231 | G8: 504 | H8: 492 | I8: 597 | J8: 321 | K8: 334 | L8: 731 | M8: 896 | N8: 1053
B9: Lease Liabilities | C9: 0 | D9: 0 | E9: 0 | F9: 0 | G9: 0 | H9: 0 | I9: 693 | J9: 764 | K9: 745 | L9: 811 | M9: 960 | N9: 1367
B10: Other Borrowings | C10: 14 | D10: 9 | E10: 8 | F10: 20 | G10: 15 | H10: 13 | I10: 11 | J10: 15 | K10: 0 | L10: 0 | M10: 0 | N10: 0
B11: Other Liabilities -
B12: Non controlling int | C12: 161 | D12: 246 | E12: 264 | F12: 384 | G12: 375 | H12: 328 | I12: 361 | J12: 404 | K12: 423 | L12: 388 | M12: 454 | N12: 695
B13: Trade Payables | C13: 1442 | D13: 1746 | E13: 1549 | F13: 1565 | G13: 1923 | H13: 2160 | I13: 2394 | J13: 2137 | K13: 3379 | L13: 4164 | M13: 3635 | N13: 3831
B14: Advance from Customers | C14: 0 | D14: 0 | E14: 5 | F14: 12 | G14: 17 | H14: 16 | I14: 13 | J14: 29 | K14: 41 | L14: 76 | M14: 108 | N14: 154
B15: Other liability items | C15: 1547 | D15: 1795 | E15: 1937 | F15: 1750 | G15: 1925 | H15: 2316 | I15: 2690 | J15: 2320 | K15: 2613 | L15: 2932 | M15: 3657 | N15: 4017
B16: Total Liabilities | C16: 6784 | D16: 8075 | E16: 8914 | F16: 10559 | G16: 12405 | H16: 13763 | I16: 16249 | J16: 16138 | K16: 20355 | L16: 22958 | M16: 25779 | N16: 29901
B18: Fixed Assets -
B19: Land | C19: 238 | D19: 247 | E19: 251 | F19: 429 | G19: 408 | H19: 586 | I19: 605 | J19: 640 | K19: 644 | L19: 644 | M19: 804 | N19: 1126
B20: Building | C20: 874 | D20: 931 | E20: 962 | F20: 923 | G20: 931 | H20: 957 | I20: 2402 | J20: 2257 | K20: 2249 | L20: 2325 | M20: 2883 | N20: 3390
B21: Plant Machinery | C21: 1956 | D21: 2054 | E21: 2132 | F21: 1793 | G21: 1980 | H21: 2157 | I21: 4006 | J21: 4208 | K21: 4340 | L21: 4531 | M21: 4825 | N21: 5422
B22: Equipments | C22: 137 | D22: 155 | E22: 171 | F22: 97 | G22: 119 | H22: 200 | I22: 221 | J22: 241 | K22: 243 | L22: 253 | M22: 270 | N22: 298
B23: Furniture n fittings | C23: 57 | D23: 71 | E23: 83 | F23: 49 | G23: 59 | H23: 72 | I23: 88 | J23: 94 | K23: 99 | L23: 113 | M23: 146 | N23: 175
B24: Vehicles | C24: 11 | D24: 14 | E24: 18 | F24: 11 | G24: 14 | H24: 27 | I24: 47 | J24: 43 | K24: 38 | L24: 32 | M24: 36 | N24: 40
B25: Intangible Assets | C25: 57 | D25: 203 | E25: 351 | F25: 339 | G25: 276 | H25: 468 | I25: 512 | J25: 505 | K25: 476 | L25: 345 | M25: 422 | N25: 850
B26: Other fixed assets | C26: 99 | D26: 128 | E26: 145 | F26: 103 | G26: 128 | H26: 238 | I26: 261 | J26: 293 | K26: 302 | L26: 294 | M26: 289 | N26: 321
B27: Gross Block | C27: 3429 | D27: 3804 | E27: 4112 | F27: 3744 | G27: 3914 | H27: 4705 | I27: 8141 | J27: 8282 | K27: 8392 | L27: 8538 | M27: 9676 | N27: 11622
B28: Accumulated Depreciation | C28: 979 | D28: 1223 | E28: 1438 | F28: 275 | G28: 610 | H28: 973 | I28: 1592 | J28: 2010 | K28: 2533 | L28: 3019 | M28: 3814 | N28: 4381
B29: Net Block | C29: =C27-C28 -> 2450 | D29: =D27-D28 -> 2581 | E29: =E27-E28 -> 2674 | F29: =F27-F28 -> 3469 | G29: =G27-G28 -> 3304 | H29: =H27-H28 -> 3732 | I29: =I27-I28 -> 6549 | J29: =J27-J28 -> 6272 | ... N29: =N27-N28 -> 7241
B30: CWIP | C30: 59 | D30: 72 | E30: 196 | F30: 107 | G30: 258 | H30: 1405 | I30: 210 | J30: 140 | K30: 183 | L30: 426 | M30: 1020 | N30: 2698
B31: Investments | C31: 296 | D31: 1424 | E31: 1588 | F31: 2712 | G31: 2652 | H31: 2141 | I31: 2569 | J31: 2019 | K31: 4737 | L31: 3248 | M31: 4262 | N31: 4588
B32: Other Assets
B33: Inventories | C33: 1830 | D33: 2070 | E33: 2259 | F33: 1998 | G33: 2627 | H33: 2658 | I33: 3150 | J33: 3390 | K33: 3799 | L33: 6153 | M33: 6211 | N33: 5923
B34: Trade receivables + | C34: 981 | D34: 1110 | E34: 1182 | F34: 1187 | G34: 1447 | H34: 1731 | I34: 1907 | J34: 1795 | K34: 2602 | L34: 3871 | M34: 4637 | N34: 4889
B35: Cash Equivalents | C35: 737 | D35: 229 | E35: 204 | F35: 424 | G35: 801 | H35: 405 | I35: 445 | J35: 783 | K35: 611 | L35: 864 | M35: 844 | N35: 1084
B36: Loans n Advances | C36: 4 | D36: 7 | E36: 8 | F36: 9 | G36: 14 | H36: 13 | I36: 16 | J36: 12 | K36: 11 | L36: 8 | M36: 12 | N36: 17
B37: Other asset items | C37: 437 | D37: 603 | E37: 817 | F37: 705 | G37: 1303 | H37: 1678 | I37: 1456 | J37: 1727 | K37: 2555 | L37: 2869 | M37: 3024 | N37: 3555
B38: Total Assets | C38: 6784 | D38: 8075 | E38: 8914 | F38: 10559 | G38: 12405 | H38: 13763 | I38: 16249 | J38: 16138 | K38: 20355 | L38: 22958 | M38: 25779 | N38: 29901
B42: Cash from Operating Activity | C42: 1187 | D42: 1402 | E42: 1188 | F42: 2243 | G42: 1527 | H42: 2113 | I42: 2470 | J42: 3038 | K42: 3683 | L42: 986 | M42: 4193 | N42: 6104
B43: Profit from operations | C43: 1784 | D43: 2051 | E43: 2271 | F43: 2848 | G43: 3056 | H43: 3274 | I43: 3861 | J43: 4380 | K43: 4970 | L43: 4957 | M43: 6460 | N43: 7929
B44: Receivables | C44: -299 | D44: -254 | E44: -155 | F44: -146 | G44: -475 | H44: -483 | I44: -205 | J44: 160 | K44: -849 | L44: -1326 | M44: -834 | N44: -362
B45: Inventory | C45: -247 | D45: -231 | E45: -144 | F45: 202 | G45: -629 | H45: -39 | I45: -492 | J45: -251 | K45: -409 | L45: -2354 | M45: -56 | N45: 315
B46: Payables | C46: 388 | D46: 317 | E46: -151 | F46: 142 | G46: 501 | H46: 442 | I46: 287 | J46: -241 | K46: 1143 | L46: 644 | M46: -539 | N46: 269
B47: Other WC items | C47: 0 | D47: 0 | E47: 0 | F47: 0 | G47: 0 | H47: 0 | I47: 0 | J47: 0 | K47: -92 | L47: 242 | M47: 657 | N47: -212
... B69: Net Cash Flow | C69: 123 | D69: 190 | E69: 147 | F69: 528 | G69: 90 | H69: -822 | I69: 434 | J69: -351 | K69: 2492 | L69: -1138 | M69: 771 | N69: 573

Sheet Forecasting
B3: ='Data Sheet'!B1&" - "&'Data Sheet'!A17&" Forecasting" -> TATA MOTORS LTD - Sales Forecasting | G3: ='Data Sheet'!B1&" - "&'Historical FS'!B18&" Forecasting" -> TATA MOTORS LTD - EBITDA Forecasting | L3: ='Data Sheet'!B1&" - "&'Historical FS'!B39&" Forecasting" -> TATA MOTORS LTD - Earning Per Share Forecasting
B4: Year Weight | C4: Year | D4: Sales | E4: Sales Growth | G4: Year Weight | H4: Year | I4: EBITDA | J4: Sales Growth | L4: Year Weight | M4: Year | N4: EPS | O4: Sales Growth
B5: 1 | C5: ='Data Sheet'!$B$16 -> 42094 | D5: {=TRANSPOSE('Data Sheet'!B17:K17)} -> 263158.98 | G5: 1 | H5: ='Data Sheet'!$B$16 -> 42094 | I5: {=TRANSPOSE('Historical FS'!C18:L18)} -> 39238.65 | L5: 1 | M5: ='Data Sheet'!$B$16 -> 42094 | N5: {=TRANSPOSE('Historical FS'!C39:L39)} -> 46.220198
B6: =B5+1 -> 2 | C6: =C5+365 -> 42459 | D6: 273045.6 | E6: =IFERROR(D6/D5-1,0) -> 0.037569001 | G6: =G5+1 -> 2 | H6: =H5+365 -> 42459 | I6: 38395.25 | J6: =IFERROR(I6/I5-1,0) -> -0.021494114 | L6: =L5+1 -> 2 | M6: =M5+365 -> 42459 | N6: 47.694444 | O6: =IFERROR(N6/N5-1,0) -> 0.031896149
B7: =B6+1 -> 3 | C7: =C6+365 -> 42824 | D7: 269692.51 | E7: =IFERROR(D7/D6-1,0) -> -0.01228033 | G7: =G6+1 -> 3 | H7: =H6+365 -> 42824 | I7: 29588.69 | J7: =IFERROR(I7/I6-1,0) -> -0.22936587 | L7: =L6+1 -> 3 | M7: =M6+365 -> 42824 | N7: 14.527275 | O7: =IFERROR(N7/N6-1,0) -> -0.6954095
B8: =B7+1 -> 4 | C8: =C7+365 -> 43189 | D8: 291550.48 | E8: =IFERROR(D8/D7-1,0) -> 0.081047746 | G8: =G7+1 -> 4 | H8: =H7+365 -> 43189 | I8: 31457.68 | J8: =IFERROR(I8/I7-1,0) -> 0.063165689 | L8: =L7+1 -> 4 | M8: =M7+365 -> 43189 | N8: 3.0491116 | O8: =IFERROR(N8/N7-1,0) -> -0.79011124
B9: =B8+1 -> 5 | C9: =C8+365 -> 43554 | D9: 301938.4 | E9: =IFERROR(D9/D8-1,0) -> 0.035629919 | G9: =G8+1 -> 5 | H9: =H8+365 -> 43554 | I9: 24664.33 | J9: =IFERROR(I9/I8-1,0) -> -0.21595203 | L9: =L8+1 -> 5 | M9: =M8+365 -> 43554 | N9: -7.7839158 | O9: =IFERROR(N9/N8-1,0) -> -3.5528471
B10: =B9+1 -> 6 | C10: =C9+365 -> 43919 | D10: 261067.97 | E10: =IFERROR(D10/D9-1,0) -> -0.13536016 | G10: =G9+1 -> 6 | H10: =H9+365 -> 43919 | I10: 17987.07 | J10: =IFERROR(I10/I9-1,0) -> -0.27072538 | L10: =L9+1 -> 6 | M10: =M9+365 -> 43919 | N10: -35.859307 | O10: =IFERROR(N10/N9-1,0) -> 3.6068468
B11: =B10+1 -> 7 | C11: =C10+365 -> 44284 | D11: 249794.75 | E11: =IFERROR(D11/D10-1,0) -> -0.043181168 | G11: =G10+1 -> 7 | H11: =H10+365 -> 44284 | I11: 32287.43 | J11: =IFERROR(I11/I10-1,0) -> 0.79503554 | L11: =L10+1 -> 7 | M11: =M10+365 -> 44284 | N11: -5.7172846 | O11: =IFERROR(N11/N10-1,0) -> -0.84056344
B12: =B11+1 -> 8 | C12: =C11+365 -> 44649 | D12: 278453.62 | E12: =IFERROR(D12/D11-1,0) -> 0.11472967 | G12: =G11+1 -> 8 | H12: =H11+365 -> 44649 | I12: 24720.09 | J12: =IFERROR(I12/I11-1,0) -> -0.23437418 | L12: =L11+1 -> 8 | M12: =M11+365 -> 44649 | N12: -41.132141 | O12: =IFERROR(N12/N11-1,0) -> 6.194349
B13: =B12+1 -> 9 | C13: =C12+365 -> 45014 | D13: 345966.97 | E13: =IFERROR(D13/D12-1,0) -> 0.24245815 | G13: =G12+1 -> 9 | H13: =H12+365 -> 45014 | I13: 31815.8 | J13: =IFERROR(I13/I12-1,0) -> 0.28704224 | L13: =L12+1 -> 9 | M13: =M12+365 -> 45014 | N13: -11.965495 | O13: =IFERROR(N13/N12-1,0) -> -0.70909622
B14: =B13+1 -> 10 | C14: =C13+365 -> 45379 | D14: 437927.77 | E14: =IFERROR(D14/D13-1,0) -> 0.26580803 | G14: =G13+1 -> 10 | H14: =H13+365 -> 45379 | I14: 59538.34 | J14: =IFERROR(I14/I13-1,0) -> 0.87134505 | L14: =L13+1 -> 10 | M14: =M13+365 -> 45379 | N14: 78.629509 | O14: =IFERROR(N14/N13-1,0) -> -7.5713542
B15: =B14+1 -> 11 | C15: =C14+365 -> 45744 | D15: =FORECAST(B15,$D$5:$D$14,$B$5:$B$14) -> 362627.59 | E15: =IFERROR(D15/D14-1,0) -> -0.17194657 | G15: =G14+1 -> 11 | H15: =H14+365 -> 45744 | I15: =FORECAST(G15,$I$5:$I$14,$G$5:$G$14) -> 36573.001 | J15: =IFERROR(I15/I14-1,0) -> -0.38572353 | L15: =L14+1 -> 11 | M15: =M14+365 -> 45744 | N15: =FORECAST(L15,$N$5:$N$14,$L$5:$L$14) -> -6.5206751 | O15: =IFERROR(N15/N14-1,0) -> -1.0829291
B16: =B15+1 -> 12 | C16: =C15+365 -> 46109 | D16: =FORECAST(B16,$D$5:$D$14,$B$5:$B$14) -> 374512.66 | E16: =IFERROR(D16/D15-1,0) -> 0.032774865 | G16: =G15+1 -> 12 | H16: =H15+365 -> 46109 | I16: =FORECAST(G16,$I$5:$I$14,$G$5:$G$14) -> 37228.214 | J16: =IFERROR(I16/I15-1,0) -> 0.017915194 | L16: =L15+1 -> 12 | M16: =M15+365 -> 46109 | N16: =FORECAST(L16,$N$5:$N$14,$L$5:$L$14) -> -9.3001141 | O16: =IFERROR(N16/N15-1,0) -> 0.42625019
B17: =B16+1 -> 13 | C17: =C16+365 -> 46474 | D17: =FORECAST(B17,$D$5:$D$14,$B$5:$B$14) -> 386397.73 | E17: =IFERROR(D17/D16-1,0) -> 0.031734763 | G17: =G16+1 -> 13 | H17: =H16+365 -> 46474 | I17: =FORECAST(G17,$I$5:$I$14,$G$5:$G$14) -> 37883.426 | J17: =IFERROR(I17/I16-1,0) -> 0.017599889 | L17: =L16+1 -> 13 | M17: =M16+365 -> 46474 | N17: =FORECAST(L17,$N$5:$N$14,$L$5:$L$14) -> -12.079553 | O17: =IFERROR(N17/N16-1,0) -> 0.29886074
B18: =B17+1 -> 14 | C18: =C17+365 -> 46839 | D18: =FORECAST(B18,$D$5:$D$14,$B$5:$B$14) -> 398282.8 | E18: =IFERROR(D18/D17-1,0) -> 0.030758644 | G18: =G17+1 -> 14 | H18: =H17+365 -> 46839 | I18: =FORECAST(G18,$I$5:$I$14,$G$5:$G$14) -> 38538.639 | J18: =IFERROR(I18/I17-1,0) -> 0.01729549 | L18: =L17+1 -> 14 | M18: =M17+365 -> 46839 | N18: =FORECAST(L18,$N$5:$N$14,$L$5:$L$14) -> -14.858992 | O18: =IFERROR(N18/N17-1,0) -> 0.23009452
B19: =B18+1 -> 15 | C19: =C18+365 -> 47204 | D19: =FORECAST(B19,$D$5:$D$14,$B$5:$B$14) -> 410167.87 | E19: =IFERROR(D19/D18-1,0) -> 0.029840782 | G19: =G18+1 -> 15 | H19: =H18+365 -> 47204 | I19: =FORECAST(G19,$I$5:$I$14,$G$5:$G$14) -> 39193.851 | J19: =IFERROR(I19/I18-1,0) -> 0.017001442 | L19: =L18+1 -> 15 | M19: =M18+365 -> 47204 | N19: =FORECAST(L19,$N$5:$N$14,$L$5:$L$14) -> -17.638431 | O19: =IFERROR(N19/N18-1,0) -> 0.18705434

Sheet Internsic Growth
B3: Calculations of ROIC | G3: ='Raw FS'!J$2 -> 43891 | H3: ='Raw FS'!K$2 -> 44256 | I3: ='Raw FS'!L$2 -> 44621 | J3: ='Raw FS'!M$2 -> 44986 | K3: ='Raw FS'!N$2 -> 45352
B5: Current Assets
B6: Inventories | G6: ='Raw FS'!J33 -> 3390 | H6: ='Raw FS'!K33 -> 3799 | I6: ='Raw FS'!L33 -> 6153 | J6: ='Raw FS'!M33 -> 6211 | K6: ='Raw FS'!N33 -> 5923
B7: Trade receivables | G7: ='Raw FS'!J34 -> 1795 | H7: ='Raw FS'!K34 -> 2602 | I7: ='Raw FS'!L34 -> 3871 | J7: ='Raw FS'!M34 -> 4637 | K7: ='Raw FS'!N34 -> 4889
B8: Loans n Advances | G8: ='Raw FS'!J36 -> 12 | H8: ='Raw FS'!K36 -> 11 | I8: ='Raw FS'!L36 -> 8 | J8: ='Raw FS'!M36 -> 12 | K8: ='Raw FS'!N36 -> 17
B9: Other asset items | G9: ='Raw FS'!J37 -> 1727 | H9: ='Raw FS'!K37 -> 2555 | I9: ='Raw FS'!L37 -> 2869 | J9: ='Raw FS'!M37 -> 3024 | K9: ='Raw FS'!N37 -> 3555
B10: Total Current Assets | G10: =SUM(G6:G9) -> 6924 | H10: =SUM(H6:H9) -> 8967 | I10: =SUM(I6:I9) -> 12901 | J10: =SUM(J6:J9) -> 13884 | K10: =SUM(K6:K9) -> 14384
B12: Current Liabilities
B13: Trade Payables | G13: ='Raw FS'!J13 -> 2137 | H13: ='Raw FS'!K13 -> 3379 | I13: ='Raw FS'!L13 -> 4164 | J13: ='Raw FS'!M13 -> 3635 | K13: ='Raw FS'!N13 -> 3831
B14: Advance from Customers | G14: ='Raw FS'!J14 -> 29 | H14: ='Raw FS'!K14 -> 41 | I14: ='Raw FS'!L14 -> 76 | J14: ='Raw FS'!M14 -> 108 | K14: ='Raw FS'!N14 -> 154
B15: Other liability items | G15: ='Raw FS'!J15 -> 2320 | H15: ='Raw FS'!K15 -> 2613 | I15: ='Raw FS'!L15 -> 2932 | J15: ='Raw FS'!M15 -> 3657 | K15: ='Raw FS'!N15 -> 4017
B16: Total Current Liabilities | G16: =SUM(G13:G15) -> 4486 | H16: =SUM(H13:H15) -> 6033 | I16: =SUM(I13:I15) -> 7172 | J16: =SUM(J13:J15) -> 7400 | K16: =SUM(K13:K15) -> 8002
A18: # | B18: Net Working Capital | G18: =G10-G16 -> 2438 | H18: =H10-H16 -> 2934 | I18: =I10-I16 -> 5729 | J18: =J10-J16 -> 6484 | K18: =K10-K16 -> 6382
B21: Non-Current Assets
B22: ='Raw FS'!B19 -> Land | G22: ='Raw FS'!J19 -> 640 | H22: ='Raw FS'!K19 -> 644 | I22: ='Raw FS'!L19 -> 644 | J22: ='Raw FS'!M19 -> 804 | K22: ='Raw FS'!N19 -> 1126
B23: ='Raw FS'!B20 -> Building | G23: ='Raw FS'!J20 -> 2257 | H23: ='Raw FS'!K20 -> 2249 | I23: ='Raw FS'!L20 -> 2325 | J23: ='Raw FS'!M20 -> 2883 | K23: ='Raw FS'!N20 -> 3390
B24: ='Raw FS'!B21 -> Plant Machinery | G24: ='Raw FS'!J21 -> 4208 | H24: ='Raw FS'!K21 -> 4340 | I24: ='Raw FS'!L21 -> 4531 | J24: ='Raw FS'!M21 -> 4825 | K24: ='Raw FS'!N21 -> 5422
B25: ='Raw FS'!B22 -> Equipments | G25: ='Raw FS'!J22 -> 241 | H25: ='Raw FS'!K22 -> 243 | I25: ='Raw FS'!L22 -> 253 | J25: ='Raw FS'!M22 -> 270 | K25: ='Raw FS'!N22 -> 298
B26: ='Raw FS'!B23 -> Furniture n fittings | G26: ='Raw FS'!J23 -> 94 | H26: ='Raw FS'!K23 -> 99 | I26: ='Raw FS'!L23 -> 113 | J26: ='Raw FS'!M23 -> 146 | K26: ='Raw FS'!N23 -> 175
B27: ='Raw FS'!B24 -> Vehicles | G27: ='Raw FS'!J24 -> 43 | H27: ='Raw FS'!K24 -> 38 | I27: ='Raw FS'!L24 -> 32 | J27: ='Raw FS'!M24 -> 36 | K27: ='Raw FS'!N24 -> 40
B28: ='Raw FS'!B25 -> Intangible Assets | G28: ='Raw FS'!J25 -> 505 | H28: ='Raw FS'!K25 -> 476 | I28: ='Raw FS'!L25 -> 345 | J28: ='Raw FS'!M25 -> 422 | K28: ='Raw FS'!N25 -> 850
B29: ='Raw FS'!B26 -> Other fixed assets | G29: ='Raw FS'!J26 -> 293 | H29: ='Raw FS'!K26 -> 302 | I29: ='Raw FS'!L26 -> 294 | J29: ='Raw FS'!M26 -> 289 | K29: ='Raw FS'!N26 -> 321
B30: Gross Block | G30: =SUM(G22:G29) -> 8281 | H30: =SUM(H22:H29) -> 8391 | I30: =SUM(I22:I29) -> 8537 | J30: =SUM(J22:J29) -> 9675 | K30: =SUM(K22:K29) -> 11622
B31: Accumulated Dpreication | G31: =-'Raw FS'!J28 -> -2010 | H31: =-'Raw FS'!K28 -> -2533 | I31: =-'Raw FS'!L28 -> -3019 | J31: =-'Raw FS'!M28 -> -3814 | K31: =-'Raw FS'!N28 -> -4381
A32: # | B32: Net Non Current Assets | G32: =SUM(G30:G31) -> 6271 | H32: =SUM(H30:H31) -> 5858 | I32: =SUM(I30:I31) -> 5518 | J32: =SUM(J30:J31) -> 5861 | K32: =SUM(K30:K31) -> 7241
A34: # | B34: Invested capital | G34: =G32+G18 -> 8709 | H34: =H32+H18 -> 8792 | I34: =I32+I18 -> 11247 | J34: =J32+J18 -> 12345 | K34: =K32+K18 -> 13623
A35: # | B35: EBIT | G35: ='Historical FS'!H27+'Historical FS'!H21 -> -3438.36 | H35: ='Historical FS'!I27+'Historical FS'!I21 -> 8740.72 | I35: ='Historical FS'!J27+'Historical FS'!J21 -> -115.6 | J35: ='Historical FS'!K27+'Historical FS'!K21 -> 6955.44 | K35: ='Historical FS'!L27+'Historical FS'!L21 -> 32268.21
A37: # | B37: ROIC | G37: =G35/G34 -> -0.39480537 | H37: =H35/H34 -> 0.99416742 | I37: =I35/I34 -> -0.010278296 | J37: =J35/J34 -> 0.56342163 | K37: =K35/K34 -> 2.3686567
A39: # | B39: Calculations of Reinvestment Rate | G39: ='Raw FS'!J$2 -> 43891 | H39: ='Raw FS'!K$2 -> 44256 | I39: ='Raw FS'!L$2 -> 44621 | J39: ='Raw FS'!M$2 -> 44986 | K39: ='Raw FS'!N$2 -> 45352
B41: Net Capex | G41: =-SUM('Raw FS'!J51:J52) -> 367 | H41: =-SUM('Raw FS'!K51:K52) -> 254 | I41: =-SUM('Raw FS'!L51:L52) -> 511 | J41: =-SUM('Raw FS'!M51:M52) -> 1420 | K41: =-SUM('Raw FS'!N51:N52) -> 2491
B42: Change in Working Capital | H42: =H18-G18 -> 496 | I42: =I18-H18 -> 2795 | J42: =J18-I18 -> 755 | K42: =K18-J18 -> -102
B44: EBIT | G44: =G35 -> -3438.36 | H44: =H35 -> 8740.72 | I44: =I35 -> -115.6 | J44: =J35 -> 6955.44 | K44: =K35 -> 32268.21
B45: Marginal Tax Rate | G45: 0.25 | H45: 0.25 | I45: 0.25 | J45: 0.25 | K45: 0.25
B46: EBIT(1-T) | G46: =G44*(1-G45) -> -2578.77 | H46: =H44*(1-H45) -> 6555.54 | I46: =I44*(1-I45) -> -86.7 | J46: =J44*(1-J45) -> 5216.58 | K46: =K44*(1-K45) -> 24201.158
B48: Reinvestment | G48: =SUM(G41:G42) -> 367 | H48: =SUM(H41:H42) -> 750 | I48: =SUM(I41:I42) -> 3306 | J48: =SUM(J41:J42) -> 2175 | K48: =SUM(K41:K42) -> 2389
B50: Reinvestment Rate | H50: =H48/H46 -> 0.11440705 | I50: =I48/I46 -> -38.131488 | J50: =J48/J46 -> 0.41693983 | K50: =K48/K46 -> 0.098714287
I52: 4 Years Average | K52: =AVERAGE(H50:K50) -> -9.3753567
I53: 4 Years Median | K53: =MEDIAN(H50:K50) -> 0.10656067
A55: # | B55: Calculations of Growth Rate | G55: ='Raw FS'!J$2 -> 43891 | H55: ='Raw FS'!K$2 -> 44256 | I55: ='Raw FS'!L$2 -> 44621 | J55: ='Raw FS'!M$2 -> 44986 | K55: ='Raw FS'!N$2 -> 45352
B57: Reinvesment Rate | H57: =H50 -> 0.11440705 | I57: =I50 -> -38.131488 | J57: =J50 -> 0.41693983 | K57: =K50 -> 0.098714287
B58: ROIC | H58: =H37 -> 0.99416742 | I58: =I37 -> -0.010278296 | J58: =J37 -> 0.56342163 | K58: =K37 -> 2.3686567
B60: Interinsic Growth | H60: =H57*H58 -> 0.11373976 | I60: =I57*I58 -> 0.39192674 | J60: =J57*J58 -> 0.23491292 | K60: =K57*K58 -> 0.23382025
I62: 4 Years Average | K62: =AVERAGE(H60:K60) -> 0.24359992
I63: 4 Years Median | K63: =MEDIAN(H60:K60) -> 0.23436659

Sheet DCF
B2: Calculation of PV of FCFF | D2: ='Internsic Growth'!K3 -> 45352 | E2: =D2+365 -> 45717 | F2: =E2+365 -> 46082 | G2: =F2+365 -> 46447 | H2: =G2+366 -> 46813 | I2: =H2+366 -> 47179
B4: EBIT | D4: ='Data Sheet'!K35 -> 37533.21 | E4: =D4*(1+$C$14) -> 45321.351 | F4: =E4*(1+$C$14) -> 54725.531 | G4: =F4*(1+$C$14) -> 66081.079 | H4: =G4*(1+$C$14) -> 79792.903 | I4: =H4*(1+$C$14) -> 96349.931
B5: Tax Rate | D5: 0.25 | E5: =D5 -> 0.25 | F5: =E5 -> 0.25 | G5: =F5 -> 0.25 | H5: =G5 -> 0.25 | I5: =G5 -> 0.25
B6: EBIT (1-Tax rate) | D6: =D4*(1-D5) -> 28149.908 | E6: =E4*(1-E5) -> 33991.013 | F6: =F4*(1-F5) -> 41044.149 | G6: =G4*(1-G5) -> 49560.809 | H6: =H4*(1-H5) -> 59844.677 | I6: =I4*(1-I5) -> 72262.448
B7: Less: Reinvestment Rate | D7: ='Internsic Growth'!K53 -> 0.10656067 | E7: =D7+(($I$7-$D$7)/4) -> 0.1115705 | F7: =E7+(($I$7-$D$7)/4) -> 0.11658033 | G7: =F7+(($I$7-$D$7)/4) -> 0.12159017 | H7: =G7+(($I$7-$D$7)/4) -> 0.1266 | I7: 0.1266
B8: Free Cash Flow to Firm (FCFF) | D8: =D6*(1-D7) -> 25150.235 | E8: =E6*(1-E7) -> 30198.619 | F8: =F6*(1-F7) -> 36259.208 | G8: =G6*(1-G7) -> 43534.702 | H8: =H6*(1-H7) -> 52268.341 | I8: =I6*(1-I7) -> 63114.022
B9: Mid Year Convention | E9: 0.5 | F9: =E9+1 -> 1.5 | G9: =F9+1 -> 2.5 | H9: =G9+1 -> 3.5 | I9: =H9+1 -> 4.5
B10: Discounting Factor | E10: =1/(1+$C$16)^E9 -> 0.94011123 | F10: =1/(1+$C$16)^F9 -> 0.83087888 | G10: =1/(1+$C$16)^G9 -> 0.73433834 | H10: =1/(1+$C$16)^H9 -> 0.64901492 | I10: =1/(1+$C$16)^I9 -> 0.57360531
B12: PV of FCFF | E12: =E8*E10 -> 28390.061 | F12: =F8*F10 -> 30127.01 | G12: =G8*G10 -> 31969.201 | H12: =H8*H10 -> 33922.933 | I12: =I8*I10 -> 36202.538
B14: Expected Growth | C14: 0.2075
B15: Terminal Growth | C15: 0.0589
B16: WACC | C16: 0.13146603
B18: Calculation of Terminal Value | F18: Sensitivity Analysis
F19: =C30 -> 493041.86 | G19: 0.11 | H19: 0.1315 | I19: 0.15 | J19: 0.17
B20: FCFF (n+1) | C20: =I8*(1+C14) -> 76210.182 | F20: 0.03 | G20: 558016.86 | H20: 493041.88 | I20: 452042.16 | J20: 417756.22
B21: WACC | C21: 0.1315 | F21: 0.0589 | G21: 558016.84 | H21: 493041.86 | I21: 452042.14 | J21: 417756.21
B22: Terminal Growth rate | C22: 0.0589 | F22: 0.07 | G22: 558016.84 | H22: 493041.85 | I22: 452042.13 | J22: 417756.2
F23: 0.09 | G23: 558016.83 | H23: 493041.84 | I23: 452042.12 | J23: 417756.19
B24: Terminal Value | C24: =C20/C21-C22 -> 579545.05
B26: Calculation of Equity Value
B28: PV of FCFF | C28: =SUM(E12:I12) -> 160611.74
B29: PV of Terminal Value | C29: =C24*I10 -> 332430.12
B30: Value of OperatingAssets | C30: =SUM(C28:C29) -> 493041.86
B32: Add: cash | C32: ='Data Sheet'!K68 -> 45806.69
B33: Less: Debt | C33: =SUM('Raw FS'!N7:N8) -> 1107
B34: Value of Equity | C34: =C30+C32-C33 -> 537741.55
B35: No. of Equity Shares | C35: ='Data Sheet'!B6 -> 368.11892
B37: Equity Value per Share | C37: =C34/C35 -> 1460.7822
